[
    {
        "category": {
            "name": "Men's Facewash",
            "id": "1498",
            "slug": "mens-facewash"
        },
        "bengaliName": "\u09b9\u09bf\u09ae\u09be\u09b2\u09df\u09be \u0985\u09cd\u09af\u09be\u09b2\u09cb\u09ad\u09c7\u09b0\u09be \u09ae\u09af\u09bc\u09b6\u09cd\u099a\u09be\u09b0\u09be\u0987\u099c\u09bf\u0982 \u09ab\u09c7\u09b8 \u0993\u09af\u09bc\u09be\u09b6 \u09e7\u09e6\u09e6 \u09ae\u09bf\u09b2\u09bf",
        "longDesc": "Origin: India\r\nManufacturer: The Himalaya drugs Ltd.\r\nHimalaya's Moisturizing Aloe Vera Face Wash is a soap-free formulation that takes care of your skin after every wash. Unlike soap, it gently cleanses without over-drying the skin. Contains Aloe vera and Cucumber.\r\nAloe Vera:\r\nAloe Vera, known for its hydrating, softening, and intense moisturizing properties, nourish the skin.\r\nCucumber:\r\nCucumber makes an excellent toner as it tightens pores. The abundant antioxidants in Cucumber are known to rejuvenate the skin and leave it feeling soft and smooth.",
        "name": "Himalaya Aloevera Moisturizing Face Wash 100 ml",
        "nameWithoutSubText": "Himalaya Aloevera Moisturizing Face Wash",
        "picturesUrls": [
            "https://chaldn.com/_mpimage/himalaya-aloevera-moisturizing-face-wash-100-ml?src=https%3A%2F%2Feggyolk.chaldal.com%2Fapi%2FPicture%2FRaw%3FpictureId%3D62745&q=low&v=1"
        ],
        "price": 159.0,
        "corpPrice": 159.0,
        "objectID": 21992
    },
    {
        "category": {
            "name": "Men's Facewash",
            "id": "1498",
            "slug": "mens-facewash"
        },
        "bengaliName": "\u09b9\u09bf\u09ae\u09be\u09b2\u09af\u09bc \u0993\u09df\u09c7\u09b2 \u0995\u09cd\u09b2\u09bf\u09af\u09bc\u09be\u09b0 \u09b2\u09c7\u09ae\u09a8 \u09ab\u09c7\u09b8 \u0993\u09af\u09bc\u09be\u09b6 \u09e7\u09e6\u09e6 \u09ae\u09bf\u09b2\u09bf",
        "longDesc": "Origin: Bangladesh\r\nManufacturer: The Himalaya drugs Ltd.\r\nHimalaya's Oil Clear Lemon Face Wash is a soap-free, formulation that gently cleanses your face and removes excess oil.\r\nHoney\r\nHoney is very beneficial for the skin as it possesses the property of attracting water to maintain moisture as well as providing nourishment to the skin.\r\nLemon\r\nLemon has an overall soothing and astringent effect. Lemon is known to remove grime and dirt and leaves your skin feeling soft and smooth.",
        "name": "Himalaya Oil Clear Lemon Face Wash 100 ml",
        "nameWithoutSubText": "Himalaya Oil Clear Lemon Face Wash",
        "picturesUrls": [
            "https://chaldn.com/_mpimage/himalaya-oil-clear-lemon-face-wash-100-ml?src=https%3A%2F%2Feggyolk.chaldal.com%2Fapi%2FPicture%2FRaw%3FpictureId%3D62743&q=low&v=1"
        ],
        "price": 119.0,
        "corpPrice": 119.0,
        "objectID": 21991
    },
    {
        "category": {
            "name": "Men's Facewash",
            "id": "1498",
            "slug": "mens-facewash"
        },
        "bengaliName": "\u09b8\u09cd\u099f\u09c1\u09a1\u09bf\u0993 \u098f\u0995\u09cd\u09b8 \u09ac\u09cd\u09b0\u09be\u0987\u099f\u09a8\u09bf\u0982 \u09ae\u09c7\u09a8 \u09ab\u09c7\u09b8 \u0993\u09af\u09bc\u09be\u09b6 \u09eb\u09e6 \u09ae\u09bf\u09b2\u09bf",
        "longDesc": "Get Ready to say goodbye to dirt once and for all and confidently show your style to the world. Introducing Studio X Brightening Facewash for Men made especially for men.",
        "name": "Studio X Brightening Men Face Wash 50 ml\t",
        "nameWithoutSubText": "Studio X Brightening Men Face Wash",
        "picturesUrls": [
            "https://chaldn.com/_mpimage/studio-x-brightening-men-face-wash-50-ml?src=https%3A%2F%2Feggyolk.chaldal.com%2Fapi%2FPicture%2FRaw%3FpictureId%3D68107&q=low&v=1"
        ],
        "price": 92.0,
        "corpPrice": 92.0,
        "objectID": 20898
    },
    {
        "category": {
            "name": "Men's Facewash",
            "id": "1498",
            "slug": "mens-facewash"
        },
        "bengaliName": "\u09b8\u09cd\u0995\u09bf\u09a8 \u0995\u099f\u09c7\u099c \u099c\u09c7\u09a8\u09cd\u099f\u09c7\u09b2 \u09ab\u09c7\u09b8\u09bf\u09df\u09be\u09b2 \u0995\u09cd\u09b2\u09bf\u09a8\u099c\u09be\u09b0 (\u09a4\u09c8\u09b2\u09be\u0995\u09cd\u09a4 \u09a4\u09cd\u09ac\u0995)  \u09e7\u09eb\u09e6 \u09ae\u09bf\u09b2\u09bf ",
        "longDesc": null,
        "name": "Skin Cottage Gentle Facial Cleanser (For Oily Skin Types) 150 ml",
        "nameWithoutSubText": "Skin Cottage Gentle Facial Cleanser (For Oily Skin Types)",
        "picturesUrls": [
            "https://chaldn.com/_mpimage/skin-cottage-gentle-facial-cleanser-for-oily-skin-types-150-ml?src=https%3A%2F%2Feggyolk.chaldal.com%2Fapi%2FPicture%2FRaw%3FpictureId%3D70375&q=low&v=1"
        ],
        "price": 450.0,
        "corpPrice": 450.0,
        "objectID": 22646
    },
    {
        "category": {
            "name": "Men's Facewash",
            "id": "1498",
            "slug": "mens-facewash"
        },
        "bengaliName": "\u09ac\u09be\u09af\u09bc\u09cb\u09b0 \u09ae\u09c7\u09a8\u09cd\u09b8 \u09b9\u09c1\u09df\u09be\u0987\u099f \u098f\u09a8\u09be\u09b0\u09cd\u099c\u09bf \u09ab\u09c7\u09b8 \u0993\u09af\u09bc\u09be\u09b6 \u09e7\u09e6\u09e6 \u0997\u09cd\u09b0\u09be\u09ae",
        "longDesc": null,
        "name": "Biore Men's White Energy Face Wash 100 gm ",
        "nameWithoutSubText": "Biore Men's White Energy Face Wash",
        "picturesUrls": [
            "https://chaldn.com/_mpimage/biore-mens-white-energy-face-wash-100-gm?src=https%3A%2F%2Feggyolk.chaldal.com%2Fapi%2FPicture%2FRaw%3FpictureId%3D67709&q=best&v=1"
        ],
        "price": 380.0,
        "corpPrice": 380.0,
        "objectID": 22521
    },
    {
        "category": {
            "name": "Men's Facewash",
            "id": "1498",
            "slug": "mens-facewash"
        },
        "bengaliName": "\u09ac\u09be\u09af\u09bc\u09cb\u09b0 \u09ae\u09c7\u09a8\u09cd\u09b8 \u098f\u0995\u09a8\u09bf \u09ac\u09cd\u09af\u09be\u0995\u099f\u09bf\u09b0\u09bf\u09af\u09bc\u09be\u09b0 \u09ab\u09c7\u09b8 \u0993\u09af\u09bc\u09be\u09b6 \u09e7\u09e6\u09e6 \u0997\u09cd\u09b0\u09be\u09ae",
        "longDesc": null,
        "name": "Biore Men's Acne Bacterior Face Wash 100 gm",
        "nameWithoutSubText": "Biore Men's Acne Bacterior Face Wash",
        "picturesUrls": [
            "https://chaldn.com/_mpimage/biore-mens-acne-bacterior-face-wash-100-gm?src=https%3A%2F%2Feggyolk.chaldal.com%2Fapi%2FPicture%2FRaw%3FpictureId%3D67708&q=low&v=1"
        ],
        "price": 380.0,
        "corpPrice": 380.0,
        "objectID": 22520
    },
    {
        "category": {
            "name": "Men's Facewash",
            "id": "1498",
            "slug": "mens-facewash"
        },
        "bengaliName": "\u09b9\u09bf\u09ae\u09be\u09b2\u09df\u09be \u099c\u09c7\u09a8\u09cd\u099f\u09be\u09b2 \u098f\u0995\u09cd\u09b8\u09ab\u09cb\u09b2\u09bf\u09af\u09bc\u09c7\u099f\u09bf\u0982 \u0993\u09af\u09bc\u09be\u09b2\u09a8\u09be\u099f \u09b8\u09cd\u0995\u09cd\u09b0\u09be\u09ac \u09e7\u09e6\u09e6 \u09ae\u09bf\u09b2\u09bf",
        "longDesc": "Origin: India\r\nManufacturer: The Himalaya drugs Ltd.\r\n\r\nRemoves dead skin cells and blackheads. Helps stimulate cell renewal.\r\nHimalaya\u2019s Gentle Exfoliating Walnut Scrub exfoliates dead skin to remove impurities that routine cleansing cannot tackle. contains crab apple, wallnut shell, wheat germ oil.\r\nCrab Apple\r\nCrab Apple has skin soothing and skin conditioning properties.\r\n \r\nWalnut Shell\r\nThe exfoliating in Walnut Shell powder scrub away dirt, blackheads and dead skin cells.\r\n \r\nWheat Germ Oil\r\nDue to its high concentration of Vitamin E and natural antioxidants, Wheat Germ Oil is ideal for most skin types. It is the perfect ingredient for our face scrub as it nourishes and improves skin texture.",
        "name": "Himalaya Gentle Exfoliating Walnut Scrub 100 ml",
        "nameWithoutSubText": "Himalaya Gentle Exfoliating Walnut Scrub",
        "picturesUrls": [
            "https://chaldn.com/_mpimage/himalaya-gentle-exfoliating-walnut-scrub-100-ml?src=https%3A%2F%2Feggyolk.chaldal.com%2Fapi%2FPicture%2FRaw%3FpictureId%3D62755&q=low&v=1"
        ],
        "price": 199.0,
        "corpPrice": 199.0,
        "objectID": 22000
    },
    {
        "category": {
            "name": "Men's Facewash",
            "id": "1498",
            "slug": "mens-facewash"
        },
        "bengaliName": "\u09b9\u09bf\u09ae\u09be\u09b2\u09df\u09be \u09ae\u09c7\u09a8 \u09aa\u09be\u0993\u09af\u09bc\u09be\u09b0 \u0997\u09cd\u09b2\u09cb \u09b2\u09bf\u0995\u09cb\u09b0\u09be\u0987\u09b8 \u09ab\u09c7\u09b8 \u0993\u09af\u09bc\u09be\u09b6 \u09e7\u09e6\u09e6 \u09ae\u09bf\u09b2\u09bf",
        "longDesc": "Origin: India\r\nManufacturer: The Himalaya drugs Ltd.\r\n\r\nFor visibly fairer and brighter skin\r\nHimalaya Men Power Glow Licorice Face Wash is a soap-free formula that gently cleanses the face. Contains alfalfa, licorice and wood apple\r\nAlfalfa\r\nAlfalfa is known to possess antioxidant and skin conditioning property.\r\n \r\nLicorice\r\nLicorice known to have skin complexion enhancing properties.\r\n \r\nWood Apple\r\nWood Apple shell powder gently exfoliates dead skin cells.",
        "name": "Himalaya Men Power Glow Licorice Face Wash 100 ml",
        "nameWithoutSubText": "Himalaya Men Power Glow Licorice Face Wash",
        "picturesUrls": [
            "https://chaldn.com/_mpimage/himalaya-men-power-glow-licorice-face-wash-100-ml?src=https%3A%2F%2Feggyolk.chaldal.com%2Fapi%2FPicture%2FRaw%3FpictureId%3D62752&q=low&v=1"
        ],
        "price": 275.0,
        "corpPrice": 275.0,
        "objectID": 21998
    },
    {
        "category": {
            "name": "Men's Facewash",
            "id": "1498",
            "slug": "mens-facewash"
        },
        "bengaliName": "\u09b9\u09bf\u09ae\u09be\u09b2\u09df\u09be \u09ae\u09cd\u09af\u09be\u09a8 \u0987\u09a8\u09cd\u099f\u09c7\u09a8\u09cd\u09b8 \u0993\u09df\u09c7\u09b2 \u0995\u09cd\u09b2\u09bf\u09df\u09be\u09b0 \u09ab\u09c7\u09b8 \u0993\u09af\u09bc\u09be\u09b6 \u09e7\u09e6\u09e6 \u09ae\u09bf\u09b2\u09bf",
        "longDesc": "Origin: India\r\nManufacturer: The Himalaya Drugs Ltd.\r\nHimalaya Men Intense Oil Clear Lemon Face Wash has been specially designed for men\u2019s skin.\r\n\r\nIndian Willow\r\nIndian Willow is rich in polyphenols which are known to exert skin conditioning and protectant activity.\r\n \r\nLemon\r\nLemon is a well-known astringent, known to remove excess oil.",
        "name": "Himalaya Men Intense Oil Clear Face Wash 100 ml",
        "nameWithoutSubText": "Himalaya Men Intense Oil Clear Face Wash",
        "picturesUrls": [
            "https://chaldn.com/_mpimage/himalaya-men-intense-oil-clear-face-wash-100-ml?src=https%3A%2F%2Feggyolk.chaldal.com%2Fapi%2FPicture%2FRaw%3FpictureId%3D62751&q=low&v=1"
        ],
        "price": 160.0,
        "corpPrice": 160.0,
        "objectID": 21997
    },
    {
        "category": {
            "name": "Men's Facewash",
            "id": "1498",
            "slug": "mens-facewash"
        },
        "bengaliName": "\u09b9\u09bf\u09ae\u09be\u09b2\u09df\u09be \u09ae\u09c7\u09a8 \u09aa\u09bf\u09ae\u09cd\u09aa\u09b2 \u0995\u09cd\u09b2\u09bf\u09af\u09bc\u09be\u09b0 \u09a8\u09bf\u09ae \u09ab\u09c7\u09b8 \u0993\u09af\u09bc\u09be\u09b6 \u09e7\u09e6\u09e6 \u09ae\u09bf\u09b2\u09bf",
        "longDesc": "Origin: India\r\nManufacturer: The Himalaya Drugs Ltd.\r\nFast and strong action on pimples.\r\nHimalaya Men Pimple Clear Neem Face Wash is a soap-free formulation that helps fight pimples in men.\r\n\r\nNatural Salicylic Extract\r\nNatural Salicylic helps unclog pores and reduce pimples.\r\n \r\nNeem\r\nNeem is known to fight effectively against pimples.",
        "name": "Himalaya Men Pimple Clear Neem Face Wash 100 ml",
        "nameWithoutSubText": "Himalaya Men Pimple Clear Neem Face Wash",
        "picturesUrls": [
            "https://chaldn.com/_mpimage/himalaya-men-pimple-clear-neem-face-wash-100-ml?src=https%3A%2F%2Feggyolk.chaldal.com%2Fapi%2FPicture%2FRaw%3FpictureId%3D62750&q=low&v=1"
        ],
        "price": 199.0,
        "corpPrice": 199.0,
        "objectID": 21995
    },
    {
        "category": {
            "name": "Men's Facewash",
            "id": "1498",
            "slug": "mens-facewash"
        },
        "bengaliName": "\u09a8\u09bf\u09ad\u09bf\u09df\u09be \u09ae\u09c7\u09a8 \u09a1\u09bf\u09aa \u09ab\u09c7\u09b8 \u0985\u09cd\u09af\u09be\u09a8\u09cd\u09a1 \u09ac\u09bf\u09df\u09be\u09b0\u09a1 \u0993\u09af\u09bc\u09be\u09b6 \u09e7\u09e6\u09e6 \u09ae\u09bf\u09b2\u09bf",
        "longDesc": null,
        "name": "Nivea Men Deep Face & Beard Wash 100 ml",
        "nameWithoutSubText": "Nivea Men Deep Face & Beard Wash",
        "picturesUrls": [
            "https://chaldn.com/_mpimage/nivea-men-deep-face-beard-wash-100-ml?src=https%3A%2F%2Feggyolk.chaldal.com%2Fapi%2FPicture%2FRaw%3FpictureId%3D74271&q=low&v=1"
        ],
        "price": 260.0,
        "corpPrice": 260.0,
        "objectID": 21886
    },
    {
        "category": {
            "name": "Men's Facewash",
            "id": "1498",
            "slug": "mens-facewash"
        },
        "bengaliName": "\u0997\u09cd\u09af\u09be\u099f\u09b8\u09ac\u09be\u0987 \u0995\u09cd\u09b2\u09bf\u09af\u09bc\u09be\u09b0 \u09b9\u09cb\u09af\u09bc\u09be\u0987\u099f\u09c7\u09a8\u09bf\u0982 \u09ab\u09c7\u09b8 \u0993\u09af\u09bc\u09be\u09b6 \u09e7\u09e8\u09e6 \u0997\u09cd\u09b0\u09be\u09ae",
        "longDesc": null,
        "name": "Gatsby Clear Whitening Face Wash 120 gm",
        "nameWithoutSubText": "Gatsby Clear Whitening Face Wash",
        "picturesUrls": [
            "https://chaldn.com/_mpimage/gatsby-clear-whitening-face-wash-120-gm?src=https%3A%2F%2Feggyolk.chaldal.com%2Fapi%2FPicture%2FRaw%3FpictureId%3D61287&q=low&v=1"
        ],
        "price": 370.0,
        "corpPrice": 370.0,
        "objectID": 21798
    },
    {
        "category": {
            "name": "Men's Facewash",
            "id": "1498",
            "slug": "mens-facewash"
        },
        "bengaliName": "\u0997\u09cd\u09af\u09be\u099f\u09b8\u09ac\u09be\u0987 \u09aa\u09be\u09b0\u09ab\u09c7\u0995\u09cd\u099f \u0995\u09cd\u09b2\u09bf\u09a8\u099c\u09bf\u0982 \u09ab\u09c7\u09b8 \u0993\u09af\u09bc\u09be\u09b6 \u09e7\u09e8\u09e6 \u0997\u09cd\u09b0\u09be\u09ae",
        "longDesc": null,
        "name": "Gatsby Perfect Cleansing Face Wash 120 gm",
        "nameWithoutSubText": "Gatsby Perfect Cleansing Face Wash",
        "picturesUrls": [
            "https://chaldn.com/_mpimage/gatsby-perfect-cleansing-face-wash-120-gm?src=https%3A%2F%2Feggyolk.chaldal.com%2Fapi%2FPicture%2FRaw%3FpictureId%3D61286&q=low&v=1"
        ],
        "price": 370.0,
        "corpPrice": 370.0,
        "objectID": 21797
    },
    {
        "category": {
            "name": "Men's Facewash",
            "id": "1498",
            "slug": "mens-facewash"
        },
        "bengaliName": "\u0997\u09cd\u09af\u09be\u099f\u09b8\u09ac\u09be\u0987 \u09aa\u09be\u0993\u09af\u09bc\u09be\u09b0 \u09b0\u09bf\u09ab\u09cd\u09b0\u09c7\u09b6\u09bf\u0982 \u09ab\u09c7\u09b8 \u0993\u09af\u09bc\u09be\u09b6 \u09e7\u09e8\u09e6 \u0997\u09cd\u09b0\u09be\u09ae",
        "longDesc": null,
        "name": "Gatsby Power Refreshing Face Wash 120 gm",
        "nameWithoutSubText": "Gatsby Power Refreshing Face Wash",
        "picturesUrls": [
            "https://chaldn.com/_mpimage/gatsby-power-refreshing-face-wash-120-gm?src=https%3A%2F%2Feggyolk.chaldal.com%2Fapi%2FPicture%2FRaw%3FpictureId%3D61283&q=low&v=1"
        ],
        "price": 370.0,
        "corpPrice": 370.0,
        "objectID": 21795
    },
    {
        "category": {
            "name": "Men's Facewash",
            "id": "1498",
            "slug": "mens-facewash"
        },
        "bengaliName": "\u09aa\u09cd\u09af\u09be\u09b0\u09be\u09b8\u09c1\u099f \u09b8\u09cd\u0995\u09bf\u09a8\u09aa\u09bf\u0993\u09b0 \u098f\u09b2\u09cb\u09ad\u09c7\u09b0\u09be \u099c\u09c7\u09b2 \u09e8\u09e6\u09e6 \u09ae\u09bf\u09b2\u09bf",
        "longDesc": "Parachute SkinPure Aloe Vera Gel is 99% pure Aloe Vera enhanced with glow boosters, which soothe & nourish skin from the inside. A 5 minutes massage every-day gives you skin that is spotless, glowing and soft to the touch.",
        "name": "Parachute SkinPure Aloe vera Gel 200ml",
        "nameWithoutSubText": "Parachute SkinPure Aloe vera Gel",
        "picturesUrls": [
            "https://chaldn.com/_mpimage/parachute-skinpure-aloe-vera-gel-200ml?src=https%3A%2F%2Feggyolk.chaldal.com%2Fapi%2FPicture%2FRaw%3FpictureId%3D60995&q=low&v=1"
        ],
        "price": 265.0,
        "corpPrice": 265.0,
        "objectID": 21620
    },
    {
        "category": {
            "name": "Men's Facewash",
            "id": "1498",
            "slug": "mens-facewash"
        },
        "bengaliName": "\u09aa\u09a8\u09cd\u09a1\u09b8 \u09aa\u09bf\u09df\u09b0 \u09b9\u09cb\u09df\u09be\u0987\u099f \u09ae\u09bf\u09a8\u09be\u09b0\u09c7\u09b2 \u0995\u09cd\u09b2\u09c7 \u098f\u09a8\u09cd\u099f\u09bf \u09aa\u09b2\u09bf\u0989\u09b6\u09a8 \u09aa\u09bf\u09df\u09b0\u09bf\u099f\u09bf \u09ab\u09c7\u09b8 \u0993\u09df\u09be\u09b6 \u09ab\u09cb\u09ae \u09ef\u09e6 \u0997\u09cd\u09b0\u09be\u09ae",
        "longDesc": null,
        "name": "Ponds Pure White Mineral Clay Anti Pollution Purity Face Wash Foam 90 gm",
        "nameWithoutSubText": "Ponds Pure White Mineral Clay Anti Pollution Purity Face Wash Foam",
        "picturesUrls": [
            "https://chaldn.com/_mpimage/ponds-pure-white-mineral-clay-anti-pollution-purity-face-wash-foam-90-gm?src=https%3A%2F%2Feggyolk.chaldal.com%2Fapi%2FPicture%2FRaw%3FpictureId%3D76231&q=low&v=1"
        ],
        "price": 225.0,
        "corpPrice": 225.0,
        "objectID": 21497
    },
    {
        "category": {
            "name": "Men's Facewash",
            "id": "1498",
            "slug": "mens-facewash"
        },
        "bengaliName": "\u09a8\u09bf\u09ad\u09bf\u09df\u09be \u09ae\u09c7\u09a8 \u098f\u0995\u09cd\u09b8\u099f\u09cd\u09b0\u09be \u09b9\u09cb\u09af\u09bc\u09be\u0987\u099f \u09a1\u09bf\u09aa \u0995\u09cd\u09b2\u09bf\u09a8 \u09e7\u09e6\u09e6 \u0997\u09cd\u09b0\u09be\u09ae",
        "longDesc": null,
        "name": "Nivea Men Extra White Deep Clean 100 gm",
        "nameWithoutSubText": "Nivea Men Extra White Deep Clean",
        "picturesUrls": [
            "https://chaldn.com/_mpimage/nivea-men-extra-white-deep-clean-100-gm?src=https%3A%2F%2Feggyolk.chaldal.com%2Fapi%2FPicture%2FRaw%3FpictureId%3D58005&q=low&v=1"
        ],
        "price": 260.0,
        "corpPrice": 260.0,
        "objectID": 21148
    },
    {
        "category": {
            "name": "Men's Facewash",
            "id": "1498",
            "slug": "mens-facewash"
        },
        "bengaliName": "\u09b8\u09cd\u099f\u09c1\u09a1\u09bf\u0993 \u098f\u0995\u09cd\u09b8 \u0993\u09af\u09bc\u09c7\u099f \u09b2\u09c1\u0995 \u09b9\u09c7\u09af\u09bc\u09be\u09b0 \u099c\u09c7\u09b2 100 \u09ae\u09bf\u09b2\u09bf",
        "longDesc": "Get the out-of-shower shiny wet look all day long, with the new improved Studio X-Wet Look. But that\u2019s not all. Your new Studio X is 100% alcohol-free and contains added Pro-Vitamin B5 to make your hair stronger.",
        "name": "Studio X Wet Look Hair Gel 100 ml",
        "nameWithoutSubText": "Studio X Wet Look Hair Gel",
        "picturesUrls": [
            "https://chaldn.com/_mpimage/studio-x-wet-look-hair-gel-100-ml?src=https%3A%2F%2Feggyolk.chaldal.com%2Fapi%2FPicture%2FRaw%3FpictureId%3D58710&q=low&v=1"
        ],
        "price": 106.0,
        "corpPrice": 106.0,
        "objectID": 21058
    },
    {
        "category": {
            "name": "Men's Facewash",
            "id": "1498",
            "slug": "mens-facewash"
        },
        "bengaliName": "\u09ac\u09be\u09af\u09bc\u09cb\u09af\u09bc\u09be\u09b0 \u09ae\u09c7\u09a8\u09b8 \u098f\u0995\u09a8\u09bf \u0985\u09cd\u09af\u09be\u0995\u09b6\u09a8 \u09ab\u09c7\u09b8 \u0993\u09af\u09bc\u09be\u09b6 \u09e7\u09e6\u09e6 \u0997\u09cd\u09b0\u09be\u09ae",
        "longDesc": null,
        "name": "Biore Mens Acne Action Face Wash 100 gm",
        "nameWithoutSubText": "Biore Mens Acne Action Face Wash",
        "picturesUrls": [
            "https://chaldn.com/_mpimage/biore-mens-acne-action-face-wash-100-gm?src=https%3A%2F%2Feggyolk.chaldal.com%2Fapi%2FPicture%2FRaw%3FpictureId%3D57757&q=low&v=1"
        ],
        "price": 370.0,
        "corpPrice": 370.0,
        "objectID": 21036
    },
    {
        "category": {
            "name": "Men's Facewash",
            "id": "1498",
            "slug": "mens-facewash"
        },
        "bengaliName": "\u09ac\u09be\u099c\u09be\u099c \u09a8\u09cb\u09ae\u09be\u09b0\u09cd\u0995\u09b8 \u0985\u09cd\u09af\u09be\u09a8\u09cd\u099f\u09bf\u09ae\u09be\u09b0\u09cd\u0995\u09b8 \u09ab\u09c7\u09b8 \u0993\u09af\u09bc\u09be\u09b6 \u09e7\u09e6\u09e6 \u0997\u09cd\u09b0\u09be\u09ae",
        "longDesc": null,
        "name": "Bajaj Nomarks Antimarks Face Wash 100 gm",
        "nameWithoutSubText": "Bajaj Nomarks Antimarks Face Wash",
        "picturesUrls": [
            "https://chaldn.com/_mpimage/bajaj-nomarks-antimarks-face-wash-100-gm?src=https%3A%2F%2Feggyolk.chaldal.com%2Fapi%2FPicture%2FRaw%3FpictureId%3D57813&q=low&v=1"
        ],
        "price": 205.0,
        "corpPrice": 205.0,
        "objectID": 21011
    },
    {
        "category": {
            "name": "Men's Facewash",
            "id": "1498",
            "slug": "mens-facewash"
        },
        "bengaliName": "\u09b0\u09c7\u09a1 \u09b9\u09be\u09a8\u09cd\u099f \u09ab\u09c7\u09b8 \u09b8\u09cd\u0995\u09cd\u09b0\u09be\u09ac \u09e7\u09e6\u09e6 \u0997\u09cd\u09b0\u09be\u09ae",
        "longDesc": null,
        "name": "Red Hunt Face Scrub 100 gm",
        "nameWithoutSubText": "Red Hunt Face Scrub",
        "picturesUrls": [
            "https://chaldn.com/_mpimage/red-hunt-face-scrub-100-gm?src=https%3A%2F%2Feggyolk.chaldal.com%2Fapi%2FPicture%2FRaw%3FpictureId%3D57524&q=low&v=1"
        ],
        "price": 395.0,
        "corpPrice": 395.0,
        "objectID": 20933
    },
    {
        "category": {
            "name": "Men's Facewash",
            "id": "1498",
            "slug": "mens-facewash"
        },
        "bengaliName": "\u09b0\u09c7\u09a1 \u09b9\u09be\u09a8\u09cd\u099f \u0985\u09af\u09bc\u09c7\u09b2 \u098f\u09a8\u09cd\u09a1 \u098f\u0995\u09a8\u09bf \u09ab\u09c7\u09b8 \u0993\u09af\u09bc\u09be\u09b6 \u09e7\u09e6\u09e6 \u0997\u09cd\u09b0\u09be\u09ae",
        "longDesc": null,
        "name": "Red Hunt Oil & Acne Face Wash 100 gm",
        "nameWithoutSubText": "Red Hunt Oil & Acne Face Wash",
        "picturesUrls": [
            "https://chaldn.com/_mpimage/red-hunt-oil-acne-face-wash-100-gm?src=https%3A%2F%2Feggyolk.chaldal.com%2Fapi%2FPicture%2FRaw%3FpictureId%3D57523&q=low&v=1"
        ],
        "price": 260.0,
        "corpPrice": 260.0,
        "objectID": 20932
    },
    {
        "category": {
            "name": "Men's Facewash",
            "id": "1498",
            "slug": "mens-facewash"
        },
        "bengaliName": "\u09b0\u09c7\u09a1 \u09b9\u09be\u09a8\u09cd\u099f \u09ab\u09c7\u09af\u09bc\u09be\u09b0\u09a8\u09c7\u09b8 \u09ab\u09c7\u09b8 \u0993\u09af\u09bc\u09be\u09b6 \u09e7\u09e6\u09e6 \u0997\u09cd\u09b0\u09be\u09ae",
        "longDesc": null,
        "name": "Red Hunt Fairness Face Wash 100 gm",
        "nameWithoutSubText": "Red Hunt Fairness Face Wash",
        "picturesUrls": [
            "https://chaldn.com/_mpimage/red-hunt-fairness-face-wash-100-gm?src=https%3A%2F%2Feggyolk.chaldal.com%2Fapi%2FPicture%2FRaw%3FpictureId%3D64893&q=low&v=1"
        ],
        "price": 260.0,
        "corpPrice": 260.0,
        "objectID": 20931
    },
    {
        "category": {
            "name": "Men's Facewash",
            "id": "1498",
            "slug": "mens-facewash"
        },
        "bengaliName": "\u09b8\u09cd\u099f\u09c1\u09a1\u09bf\u0993 \u098f\u0995\u09cd\u09b8 \u0985\u09af\u09bc\u09c7\u09b2 \u0995\u09cd\u09b2\u09bf\u09af\u09bc\u09be\u09b0 \u09ae\u09c7\u09a8 \u09ab\u09c7\u09b8 \u0993\u09af\u09bc\u09be\u09b6 \u09eb\u09e6 \u09ae\u09bf\u09b2\u09bf",
        "longDesc": "Studio X Oil Clear Face Wash has tiny energizing massage beads that clean pores from within and wash away excess oil to remove dullness, leaving your face clean and energized.",
        "name": "Studio X Oil Clear Men Face Wash 50 ml",
        "nameWithoutSubText": "Studio X Oil Clear Men Face Wash",
        "picturesUrls": [
            "https://chaldn.com/_mpimage/studio-x-oil-clear-men-face-wash-50-ml?src=https%3A%2F%2Feggyolk.chaldal.com%2Fapi%2FPicture%2FRaw%3FpictureId%3D58699&q=low&v=1"
        ],
        "price": 92.0,
        "corpPrice": 92.0,
        "objectID": 20899
    },
    {
        "category": {
            "name": "Men's Facewash",
            "id": "1498",
            "slug": "mens-facewash"
        },
        "bengaliName": "\u0997\u09be\u09b0\u09cd\u09a8\u09bf\u09af\u09bc\u09be\u09b0 \u09ae\u09c7\u09a8 \u0985\u09cd\u09af\u09be\u0995\u09a8\u09cb\u09ab\u09be\u0987\u099f \u0995\u09cd\u09b0\u09bf\u09ae \u09ea\u09eb \u0997\u09cd\u09b0\u09be\u09ae",
        "longDesc": null,
        "name": "Garnier Men Acno Fight Cream 45 gm",
        "nameWithoutSubText": "Garnier Men Acno Fight Cream",
        "picturesUrls": [
            "https://chaldn.com/_mpimage/garnier-men-acno-fight-cream-45-gm?src=https%3A%2F%2Feggyolk.chaldal.com%2Fapi%2FPicture%2FRaw%3FpictureId%3D55003&q=low&v=1"
        ],
        "price": 210.0,
        "corpPrice": 210.0,
        "objectID": 20780
    },
    {
        "category": {
            "name": "Men's Facewash",
            "id": "1498",
            "slug": "mens-facewash"
        },
        "bengaliName": "\u0997\u09be\u09b0\u09cd\u09a8\u09bf\u09af\u09bc\u09be\u09b0 \u09ae\u09c7\u09a8 \u09aa\u09be\u0993\u09af\u09bc\u09be\u09b0 \u09b9\u09cb\u09af\u09bc\u09be\u0987\u099f \u09ae\u09af\u09bc\u09b6\u09cd\u099a\u09be\u09b0\u09be\u0987\u099c\u09be\u09b0 (\u098f\u09b8\u09aa\u09bf\u098f\u09ab \u09e7\u09eb) \u09ea\u09eb \u0997\u09cd\u09b0\u09be\u09ae",
        "longDesc": null,
        "name": "Garnier Men Power White Moisturiser (SPF 15) 45 gm",
        "nameWithoutSubText": "Garnier Men Power White Moisturiser (SPF 15)",
        "picturesUrls": [
            "https://chaldn.com/_mpimage/garnier-men-power-white-moisturiser-spf-15-45-gm?src=https%3A%2F%2Feggyolk.chaldal.com%2Fapi%2FPicture%2FRaw%3FpictureId%3D55002&q=low&v=1"
        ],
        "price": 210.0,
        "corpPrice": 210.0,
        "objectID": 20779
    },
    {
        "category": {
            "name": "Men's Facewash",
            "id": "1498",
            "slug": "mens-facewash"
        },
        "bengaliName": "\u0997\u09be\u09b0\u09cd\u09a8\u09bf\u09af\u09bc\u09be\u09b0 \u09ae\u09c7\u09a8 \u09aa\u09be\u0993\u09af\u09bc\u09be\u09b0 \u09b9\u09cb\u09af\u09bc\u09be\u0987\u099f \u09ab\u09c7\u09af\u09bc\u09be\u09b0\u09a8\u09c7\u09b8 \u09ab\u09c7\u09b8 \u0993\u09af\u09bc\u09be\u09b6 \u09e7\u09e6\u09e6 \u0997\u09cd\u09b0\u09be\u09ae",
        "longDesc": null,
        "name": "Garnier Men Power White Fairness Face Wash 100 gm",
        "nameWithoutSubText": "Garnier Men Power White Fairness Face Wash",
        "picturesUrls": [
            "https://chaldn.com/_mpimage/garnier-men-power-white-fairness-face-wash-100-gm?src=https%3A%2F%2Feggyolk.chaldal.com%2Fapi%2FPicture%2FRaw%3FpictureId%3D55000&q=low&v=1"
        ],
        "price": 250.0,
        "corpPrice": 250.0,
        "objectID": 20777
    },
    {
        "category": {
            "name": "Men's Facewash",
            "id": "1498",
            "slug": "mens-facewash"
        },
        "bengaliName": "\u09b8\u09cd\u099f\u09c1\u09a1\u09bf\u0993 \u098f\u0995\u09cd\u09b8 \u0985\u09af\u09bc\u09c7\u09b2 \u0995\u09cd\u09b2\u09bf\u09af\u09bc\u09be\u09b0 \u09ae\u09cd\u09af\u09be\u09a8 \u09ab\u09c7\u09b8 \u0993\u09af\u09bc\u09be\u09b6 \u09e7\u09e6\u09e6 \u09ae\u09bf\u09b2\u09bf",
        "longDesc": "Studio X Oil Clear Face Wash has tiny energizing massage beads that clean pores from within and wash away excess oil to remove dullness, leaving your face clean and energized.",
        "name": "Studio X Oil Clear Men Face Wash 100 ml",
        "nameWithoutSubText": "Studio X Oil Clear Men Face Wash",
        "picturesUrls": [
            "https://chaldn.com/_mpimage/studio-x-oil-clear-men-face-wash-100-ml?src=https%3A%2F%2Feggyolk.chaldal.com%2Fapi%2FPicture%2FRaw%3FpictureId%3D65192&q=best&v=1"
        ],
        "price": 179.0,
        "corpPrice": 179.0,
        "objectID": 20647
    },
    {
        "category": {
            "name": "Men's Facewash",
            "id": "1498",
            "slug": "mens-facewash"
        },
        "bengaliName": "\u09b8\u09cd\u099f\u09c1\u09a1\u09bf\u0993 \u098f\u0995\u09cd\u09b8 \u09ac\u09cd\u09b0\u09be\u0987\u099f\u09c7\u09a8\u09bf\u0982 \u09ae\u09cd\u09af\u09be\u09a8 \u09ab\u09c7\u09b8 \u0993\u09af\u09bc\u09be\u09b6 \u09e7\u09e6\u09e6 \u09ae\u09bf\u09b2\u09bf",
        "longDesc": "Get Ready to say goodbye to dirt once and for all and confidently show your style to the world. Introducing Studio X Brightening Facewash for Men made especially for men.",
        "name": "Studio X Brightening Men Face Wash 100 ml",
        "nameWithoutSubText": "Studio X Brightening Men Face Wash",
        "picturesUrls": [
            "https://chaldn.com/_mpimage/studio-x-brightening-men-face-wash-100-ml?src=https%3A%2F%2Feggyolk.chaldal.com%2Fapi%2FPicture%2FRaw%3FpictureId%3D65191&q=best&v=1"
        ],
        "price": 179.0,
        "corpPrice": 179.0,
        "objectID": 20646
    },
    {
        "category": {
            "name": "Men's Facewash",
            "id": "1498",
            "slug": "mens-facewash"
        },
        "bengaliName": "\u09ac\u09be\u09af\u09bc\u09cb\u09b0 \u09ae\u09c7\u09a8 \u09ac\u09cd\u09b0\u09be\u0987\u099f \u0985\u09cd\u09af\u09be\u0995\u09b6\u09a8 \u09ab\u09c7\u09b8 \u0993\u09df\u09be\u09b6 \u09e7\u09e6\u09e6 \u0997\u09cd\u09b0\u09be\u09ae",
        "longDesc": null,
        "name": "Biore Mans Bright Action Face Wash 100 gm",
        "nameWithoutSubText": "Biore Mans Bright Action Face Wash",
        "picturesUrls": [
            "https://chaldn.com/_mpimage/biore-mans-bright-action-face-wash-100-gm?src=https%3A%2F%2Feggyolk.chaldal.com%2Fapi%2FPicture%2FRaw%3FpictureId%3D51814&q=low&v=1"
        ],
        "price": 380.0,
        "corpPrice": 380.0,
        "objectID": 19815
    },
    {
        "category": {
            "name": "Men's Facewash",
            "id": "1498",
            "slug": "mens-facewash"
        },
        "bengaliName": "\u09ac\u09be\u09af\u09bc\u09cb\u09b0 \u09ae\u09c7\u09a8 \u09a1\u09bf\u09aa \u09ab\u09cd\u09b0\u09c7\u09b6 \u09ab\u09c7\u09b8 \u0993\u09df\u09be\u09b6 \u09e7\u09e6\u09e6 \u0997\u09cd\u09b0\u09be\u09ae",
        "longDesc": null,
        "name": "Biore Mans Deep Fresh Face Wash 100 gm",
        "nameWithoutSubText": "Biore Mans Deep Fresh Face Wash",
        "picturesUrls": [
            "https://chaldn.com/_mpimage/biore-mans-deep-fresh-face-wash-100-gm?src=https%3A%2F%2Feggyolk.chaldal.com%2Fapi%2FPicture%2FRaw%3FpictureId%3D66140&q=best&v=1"
        ],
        "price": 380.0,
        "corpPrice": 380.0,
        "objectID": 19814
    },
    {
        "category": {
            "name": "Men's Facewash",
            "id": "1498",
            "slug": "mens-facewash"
        },
        "bengaliName": "\u09aa\u09a8\u09cd\u09a1\u09b8 \u09ae\u09cd\u09af\u09be\u09a8 \u09ab\u09c7\u09b8 \u0993\u09df\u09be\u09b6 \u09aa\u09be\u0993\u09df\u09be\u09b0 \u0995\u09cd\u09b2\u09bf\u09df\u09be\u09b0 \u09e7\u09e6\u09e6 \u0997\u09cd\u09b0\u09be\u09ae",
        "longDesc": null,
        "name": "Ponds Men Face Wash Power Clear 100 gm",
        "nameWithoutSubText": "Ponds Men Face Wash Power Clear",
        "picturesUrls": [
            "https://chaldn.com/_mpimage/ponds-men-face-wash-power-clear-100-gm?src=https%3A%2F%2Feggyolk.chaldal.com%2Fapi%2FPicture%2FRaw%3FpictureId%3D77715&q=low&v=1"
        ],
        "price": 240.0,
        "corpPrice": 240.0,
        "objectID": 18623
    },
    {
        "category": {
            "name": "Men's Facewash",
            "id": "1498",
            "slug": "mens-facewash"
        },
        "bengaliName": "\u0987\u09ae\u09be\u09ae\u09bf \u09ab\u09c7\u09df\u09be\u09b0 \u098f\u09a8\u09cd\u09a1 \u09b9\u09cd\u09af\u09be\u09a8\u09cd\u09a1\u09b8\u09be\u09ae \u099a\u09be\u09b0\u0995\u09cb\u09b2 \u09ab\u09c7\u09b8 \u0993\u09af\u09bc\u09be\u09b6 \u09eb\u09e6 \u0997\u09cd\u09b0\u09be\u09ae",
        "longDesc": null,
        "name": "Emami Fair And Handsome Charcoal Face Wash 50 gm",
        "nameWithoutSubText": "Emami Fair And Handsome Charcoal Face Wash",
        "picturesUrls": [
            "https://chaldn.com/_mpimage/emami-fair-and-handsome-charcoal-face-wash-50-gm?src=https%3A%2F%2Feggyolk.chaldal.com%2Fapi%2FPicture%2FRaw%3FpictureId%3D64891&q=low&v=1"
        ],
        "price": 195.0,
        "corpPrice": 195.0,
        "objectID": 18603
    },
    {
        "category": {
            "name": "Men's Facewash",
            "id": "1498",
            "slug": "mens-facewash"
        },
        "bengaliName": "\u0987\u09ae\u09be\u09ae\u09bf \u09ab\u09c7\u09df\u09be\u09b0 \u098f\u09a8\u09cd\u09a1 \u09b9\u09cd\u09af\u09be\u09a8\u09cd\u09a1\u09b8\u09be\u09ae \u09aa\u09bf\u09ae\u09cd\u09aa\u09b2 \u09ab\u09c7\u09b8 \u0993\u09af\u09bc\u09be\u09b6 \u09eb\u09e6 \u0997\u09cd\u09b0\u09be\u09ae",
        "longDesc": null,
        "name": "Emami Fair And Handsome Pimple Clear Face Wash 50 gm",
        "nameWithoutSubText": "Emami Fair And Handsome Pimple Clear Face Wash",
        "picturesUrls": [
            "https://chaldn.com/_mpimage/emami-fair-and-handsome-pimple-clear-face-wash-50-gm?src=https%3A%2F%2Feggyolk.chaldal.com%2Fapi%2FPicture%2FRaw%3FpictureId%3D50393&q=low&v=1"
        ],
        "price": 150.0,
        "corpPrice": 150.0,
        "objectID": 18602
    },
    {
        "category": {
            "name": "Men's Facewash",
            "id": "1498",
            "slug": "mens-facewash"
        },
        "bengaliName": "\u0985\u0995\u09cd\u09b8\u09bf \u09ae\u09cb\u099f \u0985\u09cd\u09af\u09be\u09a8\u09cd\u099f\u09bf \u09ac\u09cd\u09b0\u09a3 \u09ab\u09c7\u09b8 \u0993\u09af\u09bc\u09be\u09b6  \u09eb\u09e6 \u0997\u09cd\u09b0\u09be\u09ae",
        "longDesc": null,
        "name": "OXY Total Anti Acne Face Wash 50 gm",
        "nameWithoutSubText": "OXY Total Anti Acne Face Wash",
        "picturesUrls": [
            "https://chaldn.com/_mpimage/oxy-total-anti-acne-face-wash-50-gm?src=https%3A%2F%2Feggyolk.chaldal.com%2Fapi%2FPicture%2FRaw%3FpictureId%3D43820&q=low&v=1"
        ],
        "price": 240.0,
        "corpPrice": 240.0,
        "objectID": 16224
    },
    {
        "category": {
            "name": "Men's Facewash",
            "id": "1498",
            "slug": "mens-facewash"
        },
        "bengaliName": "\u09aa\u09a8\u09cd\u09a1\u09b8 \u09ae\u09cd\u09af\u09be\u09a8 \u09ab\u09c7\u09b8 \u0993\u09df\u09be\u09b6 \u098f\u0995\u09a8\u09bf \u09b8\u09b2\u09cd\u09af\u09c1\u09b6\u09a8 \u09eb\u09e6 \u0997\u09cd\u09b0\u09be\u09ae",
        "longDesc": null,
        "name": "Ponds Men Face Wash Acne Solution 50 gm",
        "nameWithoutSubText": "Ponds Men Face Wash Acne Solution",
        "picturesUrls": [
            "https://chaldn.com/_mpimage/ponds-men-face-wash-acne-solution-50-gm?src=https%3A%2F%2Feggyolk.chaldal.com%2Fapi%2FPicture%2FRaw%3FpictureId%3D79128&q=low&v=1"
        ],
        "price": 135.0,
        "corpPrice": 135.0,
        "objectID": 16128
    },
    {
        "category": {
            "name": "Men's Facewash",
            "id": "1498",
            "slug": "mens-facewash"
        },
        "bengaliName": "\u09aa\u09a8\u09cd\u09a1\u09b8 \u09ae\u09cd\u09af\u09be\u09a8 \u09ab\u09c7\u09b8 \u0993\u09df\u09be\u09b6 \u098f\u0995\u09a8\u09bf \u09b8\u09b2\u09cd\u09af\u09c1\u09b6\u09a8 \u09e7\u09e6\u09e6 \u0997\u09cd\u09b0\u09be\u09ae",
        "longDesc": null,
        "name": "Ponds Men Face Wash Acne Solution 100 gm",
        "nameWithoutSubText": "Ponds Men Face Wash Acne Solution",
        "picturesUrls": [
            "https://chaldn.com/_mpimage/ponds-men-face-wash-acne-solution-100-gm?src=https%3A%2F%2Feggyolk.chaldal.com%2Fapi%2FPicture%2FRaw%3FpictureId%3D77746&q=low&v=1"
        ],
        "price": 225.0,
        "corpPrice": 225.0,
        "objectID": 16127
    },
    {
        "category": {
            "name": "Men's Facewash",
            "id": "1498",
            "slug": "mens-facewash"
        },
        "bengaliName": "\u09aa\u09a8\u09cd\u09a1\u09b8 \u09ae\u09cd\u09af\u09be\u09a8 \u09ab\u09c7\u09b8 \u0993\u09df\u09be\u09b6 \u098f\u09a8\u09be\u09b0\u09cd\u099c\u09bf \u099a\u09be\u09b0\u09cd\u099c \u09eb\u09e6 \u0997\u09cd\u09b0\u09be\u09ae",
        "longDesc": null,
        "name": "Ponds Men Face Wash Energy Charge 50 gm",
        "nameWithoutSubText": "Ponds Men Face Wash Energy Charge",
        "picturesUrls": [
            "https://chaldn.com/_mpimage/ponds-men-face-wash-energy-charge-50-gm?src=https%3A%2F%2Feggyolk.chaldal.com%2Fapi%2FPicture%2FRaw%3FpictureId%3D79130&q=low&v=1"
        ],
        "price": 135.0,
        "corpPrice": 135.0,
        "objectID": 16126
    },
    {
        "category": {
            "name": "Men's Facewash",
            "id": "1498",
            "slug": "mens-facewash"
        },
        "bengaliName": "\u09aa\u09a8\u09cd\u09a1\u09b8 \u09ae\u09cd\u09af\u09be\u09a8 \u09ab\u09c7\u09b8 \u0993\u09df\u09be\u09b6 \u098f\u09a8\u09be\u09b0\u09cd\u099c\u09bf \u099a\u09be\u09b0\u09cd\u099c \u09e7\u09e6\u09e6 \u0997\u09cd\u09b0\u09be\u09ae",
        "longDesc": null,
        "name": "Ponds Men Face Wash Energy Charge 100 gm",
        "nameWithoutSubText": "Ponds Men Face Wash Energy Charge",
        "picturesUrls": [
            "https://chaldn.com/_mpimage/ponds-men-face-wash-energy-charge-100-gm?src=https%3A%2F%2Feggyolk.chaldal.com%2Fapi%2FPicture%2FRaw%3FpictureId%3D79129&q=low&v=1"
        ],
        "price": 225.0,
        "corpPrice": 225.0,
        "objectID": 16125
    },
    {
        "category": {
            "name": "Men's Facewash",
            "id": "1498",
            "slug": "mens-facewash"
        },
        "bengaliName": "\u09aa\u09a8\u09cd\u09a1\u09b8 \u09ae\u09cd\u09af\u09be\u09a8 \u09ab\u09c7\u09b8 \u0993\u09df\u09be\u09b6 \u09b2\u09be\u0987\u099f\u09a8\u09bf\u0982 \u0985\u09df\u09c7\u09b2 \u0995\u09cd\u09b2\u09bf\u09df\u09be\u09b0 \u09eb\u09e6 \u0997\u09cd\u09b0\u09be\u09ae",
        "longDesc": null,
        "name": "Ponds Men Face Wash Lightning Oil Clear 50 gm",
        "nameWithoutSubText": "Ponds Men Face Wash Lightning Oil Clear",
        "picturesUrls": [
            "https://chaldn.com/_mpimage/ponds-men-face-wash-lightning-oil-clear-50-gm?src=https%3A%2F%2Feggyolk.chaldal.com%2Fapi%2FPicture%2FRaw%3FpictureId%3D79133&q=low&v=1"
        ],
        "price": 135.0,
        "corpPrice": 135.0,
        "objectID": 16124
    },
    {
        "category": {
            "name": "Men's Facewash",
            "id": "1498",
            "slug": "mens-facewash"
        },
        "bengaliName": "\u09aa\u09a8\u09cd\u09a1\u09b8 \u09ae\u09cd\u09af\u09be\u09a8 \u09ab\u09c7\u09b8 \u0993\u09df\u09be\u09b6 \u09b2\u09be\u0987\u099f\u09a8\u09bf\u0982 \u0985\u09df\u09c7\u09b2 \u0995\u09cd\u09b2\u09bf\u09df\u09be\u09b0 \u09e7\u09e6\u09e6 \u0997\u09cd\u09b0\u09be\u09ae",
        "longDesc": null,
        "name": "Ponds Men Face Wash Lightning Oil Clear 100 gm",
        "nameWithoutSubText": "Ponds Men Face Wash Lightning Oil Clear",
        "picturesUrls": [
            "https://chaldn.com/_mpimage/ponds-men-face-wash-lightning-oil-clear-100-gm?src=https%3A%2F%2Feggyolk.chaldal.com%2Fapi%2FPicture%2FRaw%3FpictureId%3D79131&q=low&v=1"
        ],
        "price": 216.0,
        "corpPrice": 216.0,
        "objectID": 16123
    },
    {
        "category": {
            "name": "Men's Facewash",
            "id": "1498",
            "slug": "mens-facewash"
        },
        "bengaliName": "\u09ae\u09cd\u09af\u09be\u09a8\u09b8 \u0997\u09cd\u09b2\u09cb \u0985\u09cd\u09af\u09be\u09a8\u09cd\u09a1 \u09b9\u09cd\u09af\u09be\u09a8\u09cd\u09a1\u09b8\u09be\u09ae \u09ab\u09c7\u09b8 \u0993\u09df\u09be\u09b6 \u09b0\u200d\u09cd\u09af\u09be\u09aa\u09bf\u09a1 \u098f\u0995\u09b6\u09a8 \u09e7\u09e6\u09e6 \u0997\u09cd\u09b0\u09be\u09ae",
        "longDesc": null,
        "name": "Mens Glow And Handsome Face Wash Rapid Action 100 gm",
        "nameWithoutSubText": "Mens Glow And Handsome Face Wash Rapid Action",
        "picturesUrls": [
            "https://chaldn.com/_mpimage/mens-glow-and-handsome-face-wash-rapid-action-100-gm?src=https%3A%2F%2Feggyolk.chaldal.com%2Fapi%2FPicture%2FRaw%3FpictureId%3D76187&q=low&v=1"
        ],
        "price": 160.0,
        "corpPrice": 160.0,
        "objectID": 15748
    },
    {
        "category": {
            "name": "Men's Facewash",
            "id": "1498",
            "slug": "mens-facewash"
        },
        "bengaliName": "\u09a8\u09bf\u09ad\u09bf\u09df\u09be \u09ae\u09c7\u09a8 \u09a1\u09be\u09b0\u09cd\u0995 \u09b8\u09cd\u09aa\u099f \u09b0\u09bf\u09a1\u09be\u0995\u09b6\u09a8 \u09ab\u09c7\u09b8 \u0993\u09df\u09be\u09b6 \u09e7\u09e6\u09e6 \u0997\u09cd\u09b0\u09be\u09ae",
        "longDesc": "Nivea Dark Spot Reduction Face Wash reduces the appearance of dark spots and makes skin look healthy and feel fresh. The effective 10x* formula, suitable for All Skin Types, is now even better with Whitanat Vita Complex Plus that contains 10 nutrients:\r\n\u2022 Licorice\r\n\u2022 Vitamin C\r\n\u2022 Whitanat\r\n\u2022 Vitamin E\r\n\u2022 Pro-Vitamin B5\r\n\u2022 Ginko Leaves Extract\r\n\u2022 Ginseng Root Extract\r\n\u2022 Glycerin\r\n\u2022 Magnesium Chloride\r\n\u2022 Glyceryl Glucoside\r\nSkin compatibility dermatologically approved.\r\n*in vitro test for Whitanat vs. Vitamin C\r\n\r\nResult:\r\n\u2022 Deeply cleansed skin.\r\n\u2022 Reduced dark spots accumulated from dirt and residues.\r\n\u2022 Reduced oiliness & tightened pores upto 12h.\r\n\u2022 Healthy looking & fresh feeling skin.\r\n\u2022 Reduces Dark Spots\r\n\u2022 Skin looks healthy and fresh\r\n\u2022 Contains Vitamin C & Vitamin E",
        "name": "Nivea Men Dark Spot Reduction Face Wash 100 gm",
        "nameWithoutSubText": "Nivea Men Dark Spot Reduction Face Wash",
        "picturesUrls": [
            "https://chaldn.com/_mpimage/nivea-men-dark-spot-reduction-face-wash-100-gm?src=https%3A%2F%2Feggyolk.chaldal.com%2Fapi%2FPicture%2FRaw%3FpictureId%3D22724&q=low&v=1"
        ],
        "price": 260.0,
        "corpPrice": 260.0,
        "objectID": 11982
    },
    {
        "category": {
            "name": "Men's Facewash",
            "id": "1498",
            "slug": "mens-facewash"
        },
        "bengaliName": "\u098f\u09b8\u099f\u09bf.\u0986\u0987\u09ad\u09b8 \u098f\u0995\u09a8\u09bf \u0995\u09a8\u09cd\u099f\u09cd\u09b0\u09cb\u09b2 \u098f\u09aa\u09cd\u09b0\u09bf\u0995\u09cb\u099f \u09b8\u09cd\u0995\u09cd\u09b0\u09be\u09ac \u09e8\u09ee\u09e9 \u0997\u09cd\u09b0\u09be\u09ae",
        "longDesc": null,
        "name": "ST.Ives Acne Control Apricot Scrub 283 gm",
        "nameWithoutSubText": "ST.Ives Acne Control Apricot Scrub",
        "picturesUrls": [
            "https://chaldn.com/_mpimage/stives-acne-control-apricot-scrub-283-gm?src=https%3A%2F%2Feggyolk.chaldal.com%2Fapi%2FPicture%2FRaw%3FpictureId%3D52917&q=best&v=1"
        ],
        "price": 699.0,
        "corpPrice": 699.0,
        "objectID": 11269
    },
    {
        "category": {
            "name": "Men's Facewash",
            "id": "1498",
            "slug": "mens-facewash"
        },
        "bengaliName": "\u09aa\u09a8\u09cd\u09a1'\u09b8 \u09ae\u09cd\u09af\u09be\u09a8 \u098f\u09a8\u09be\u09b0\u09cd\u099c\u09bf \u099a\u09be\u09b0\u09cd\u099c \u09ab\u09c7\u09b8 \u0993\u09df\u09be\u09b6 \u09e7\u09e6\u09e6 \u0997\u09cd\u09b0\u09be\u09ae",
        "longDesc": null,
        "name": "Pond's Men Energy Charge Face Wash 100 gm",
        "nameWithoutSubText": "Pond's Men Energy Charge Face Wash",
        "picturesUrls": [
            "https://chaldn.com/_mpimage/ponds-men-energy-charge-face-wash-100-gm?src=https%3A%2F%2Feggyolk.chaldal.com%2Fapi%2FPicture%2FRaw%3FpictureId%3D19660&q=low&v=1"
        ],
        "price": 350.0,
        "corpPrice": 350.0,
        "objectID": 11199
    },
    {
        "category": {
            "name": "Men's Facewash",
            "id": "1498",
            "slug": "mens-facewash"
        },
        "bengaliName": "\u0985\u0995\u09cd\u09b8\u09bf \u09b9\u09cb\u09df\u09be\u0987\u099f\u09a8\u09bf\u0982 \u09ab\u09c7\u09b8 \u0993\u09df\u09be\u09b6 \u09eb\u09e6 \u0997\u09cd\u09b0\u09be\u09ae",
        "longDesc": null,
        "name": "Oxy Whitening Face Wash 50 gm ",
        "nameWithoutSubText": "Oxy Whitening Face Wash",
        "picturesUrls": [
            "https://chaldn.com/_mpimage/oxy-whitening-face-wash-50-gm?src=https%3A%2F%2Feggyolk.chaldal.com%2Fapi%2FPicture%2FRaw%3FpictureId%3D25903&q=low&v=1"
        ],
        "price": 240.0,
        "corpPrice": 240.0,
        "objectID": 11079
    },
    {
        "category": {
            "name": "Men's Facewash",
            "id": "1498",
            "slug": "mens-facewash"
        },
        "bengaliName": "\u0985\u0995\u09cd\u09b8\u09bf \u09aa\u09be\u09b0\u09ab\u09c7\u0995\u09cd\u099f \u09ab\u09c7\u09b8 \u0993\u09df\u09be\u09b6 \u09eb\u09e6 \u0997\u09cd\u09b0\u09be\u09ae",
        "longDesc": null,
        "name": "OXY Perfect Face Wash 50 ml",
        "nameWithoutSubText": "OXY Perfect Face Wash",
        "picturesUrls": [
            "https://chaldn.com/_mpimage/oxy-perfect-face-wash-50-ml?src=https%3A%2F%2Feggyolk.chaldal.com%2Fapi%2FPicture%2FRaw%3FpictureId%3D25899&q=low&v=1"
        ],
        "price": 195.0,
        "corpPrice": 195.0,
        "objectID": 10783
    },
    {
        "category": {
            "name": "Men's Facewash",
            "id": "1498",
            "slug": "mens-facewash"
        },
        "bengaliName": "\u0997\u09be\u09b0\u09a8\u09bf\u09df\u09be\u09b0 \u09ae\u09c7\u09a8 \u09aa\u09be\u0993\u09df\u09be\u09b0 \u09b9\u09cb\u09df\u09be\u0987\u099f \u09ab\u09c7\u09df\u09be\u09b0\u09a8\u09c7\u09b8 \u0995\u09cd\u09b0\u09bf\u09ae \u09e8\u09e6 \u0997\u09cd\u09b0\u09be\u09ae",
        "longDesc": null,
        "name": "Garnier Men PowerWhite Fairness Cream 20 gm",
        "nameWithoutSubText": "Garnier Men PowerWhite Fairness Cream",
        "picturesUrls": [
            "https://chaldn.com/_mpimage/garnier-men-powerwhite-fairness-cream-20-gm?src=https%3A%2F%2Feggyolk.chaldal.com%2Fapi%2FPicture%2FRaw%3FpictureId%3D27599&q=low&v=1"
        ],
        "price": 120.0,
        "corpPrice": 120.0,
        "objectID": 10149
    },
    {
        "category": {
            "name": "Men's Facewash",
            "id": "1498",
            "slug": "mens-facewash"
        },
        "bengaliName": "\u0997\u09be\u09b0\u09a8\u09bf\u09df\u09be\u09b0 \u09ae\u09c7\u09a8 \u09aa\u09be\u0993\u09df\u09be\u09b0 \u09b9\u09cb\u09df\u09be\u0987\u099f \u09ab\u09c7\u09b8 \u0993\u09df\u09be\u09b6 \u09e7\u09e6\u09e6 \u0997\u09cd\u09b0\u09be\u09ae",
        "longDesc": null,
        "name": "Garnier Men Power White Fairness Face Wash 100 gm",
        "nameWithoutSubText": "Garnier Men Power White Fairness Face Wash",
        "picturesUrls": [
            "https://chaldn.com/_mpimage/garnier-men-power-white-fairness-face-wash-100-gm?src=https%3A%2F%2Feggyolk.chaldal.com%2Fapi%2FPicture%2FRaw%3FpictureId%3D40233&q=low&v=1"
        ],
        "price": 250.0,
        "corpPrice": 250.0,
        "objectID": 10125
    },
    {
        "category": {
            "name": "Men's Facewash",
            "id": "1498",
            "slug": "mens-facewash"
        },
        "bengaliName": "\u0997\u09be\u09b0\u09a8\u09bf\u09df\u09be\u09b0 \u09ae\u09cd\u09af\u09be\u09a8 \u098f\u0995\u09a8\u09cb \u09ab\u09be\u0987\u099f \u09ab\u09c7\u09b8 \u0993\u09df\u09be\u09b6 \u09e7\u09e6\u09e6 \u0997\u09cd\u09b0\u09be\u09ae",
        "longDesc": null,
        "name": "Garnier Men Acno Fight Face Wash 100 gm",
        "nameWithoutSubText": "Garnier Men Acno Fight Face Wash",
        "picturesUrls": [
            "https://chaldn.com/_mpimage/garnier-men-acno-fight-face-wash-100-gm?src=https%3A%2F%2Feggyolk.chaldal.com%2Fapi%2FPicture%2FRaw%3FpictureId%3D41742&q=low&v=1"
        ],
        "price": 250.0,
        "corpPrice": 250.0,
        "objectID": 10123
    },
    {
        "category": {
            "name": "Men's Facewash",
            "id": "1498",
            "slug": "mens-facewash"
        },
        "bengaliName": "\u09a8\u09bf\u09ad\u09bf\u09df\u09be \u09ae\u09c7\u09a8 \u09aa\u09cd\u09b0\u09cb\u099f\u09c7\u0995\u09cd\u099f \u098f\u09a8\u09cd\u09a1 \u0995\u09c7\u09df\u09be\u09b0 \u09ab\u09be\u0987\u09b8 \u0993\u09df\u09be\u09b8 \u09e7\u09e6\u09e6 \u09ae\u09bf\u09b2\u09bf",
        "longDesc": null,
        "name": "Nivea Men Protect & Care Face Wash 100 ml",
        "nameWithoutSubText": "Nivea Men Protect & Care Face Wash",
        "picturesUrls": [
            "https://chaldn.com/_mpimage/nivea-men-protect-care-face-wash-100-ml?src=https%3A%2F%2Feggyolk.chaldal.com%2Fapi%2FPicture%2FRaw%3FpictureId%3D67226&q=low&v=1"
        ],
        "price": 260.0,
        "corpPrice": 260.0,
        "objectID": 10091
    },
    {
        "category": {
            "name": "Men's Facewash",
            "id": "1498",
            "slug": "mens-facewash"
        },
        "bengaliName": "\u0985\u0995\u09cd\u09b8\u09bf \u098f\u09cd\u09af\u09be\u0995\u09cd\u099f\u09bf\u09ad \u09ab\u09c7\u09b8 \u0993\u09df\u09be\u09b6 \u09eb\u09e6 \u0997\u09cd\u09b0\u09be\u09ae",
        "longDesc": null,
        "name": "OXY Active Face Wash 50 gm",
        "nameWithoutSubText": "OXY Active Face Wash",
        "picturesUrls": [
            "https://chaldn.com/_mpimage/oxy-active-face-wash-50-gm?src=https%3A%2F%2Feggyolk.chaldal.com%2Fapi%2FPicture%2FRaw%3FpictureId%3D25904&q=low&v=1"
        ],
        "price": 240.0,
        "corpPrice": 240.0,
        "objectID": 9313
    },
    {
        "category": {
            "name": "Men's Facewash",
            "id": "1498",
            "slug": "mens-facewash"
        },
        "bengaliName": "\u0985\u0995\u09cd\u09b8\u09bf \u0993\u09df\u09c7\u09b2 \u0995\u09a8\u09cd\u099f\u09cd\u09b0\u09cb\u09b2 \u09ab\u09c7\u09b8 \u0993\u09df\u09be\u09b6 \u09eb\u09e6 \u0997\u09cd\u09b0\u09be\u09ae",
        "longDesc": null,
        "name": "OXY Oil Control Face Wash 50 gm",
        "nameWithoutSubText": "OXY Oil Control Face Wash",
        "picturesUrls": [
            "https://chaldn.com/_mpimage/oxy-oil-control-face-wash-50-gm?src=https%3A%2F%2Feggyolk.chaldal.com%2Fapi%2FPicture%2FRaw%3FpictureId%3D25900&q=low&v=1"
        ],
        "price": 240.0,
        "corpPrice": 240.0,
        "objectID": 9312
    },
    {
        "category": {
            "name": "Men's Facewash",
            "id": "1498",
            "slug": "mens-facewash"
        },
        "bengaliName": "\u0997\u09be\u09b0\u09a8\u09bf\u09df\u09be\u09b0 \u09ae\u09c7\u09a8 \u0993\u09df\u09c7\u09b2 \u0995\u09cd\u09b2\u09bf\u09df\u09be\u09b0 \u09ab\u09c7\u09b8\u0993\u09df\u09be\u09b6 \u09e7\u09e6\u09e6 \u0997\u09cd\u09b0\u09be\u09ae",
        "longDesc": "Benefits : \r\n\r\nRemoves excessive oil without drying\r\nskin.\r\nDaily use makes skin clean & fresh.\r\n\r\nFeatures :   \r\n \r\nUnique Oil Trapping Mud Texture and\r\nnatural ingredients.\r\nContains cooling Menthol",
        "name": "Garnier Men Oil Clear Clay D-Tox Icy Face wash 100 gm",
        "nameWithoutSubText": "Garnier Men Oil Clear Clay D-Tox Icy Face wash",
        "picturesUrls": [
            "https://chaldn.com/_mpimage/garnier-men-oil-clear-clay-d-tox-icy-face-wash-100-gm?src=https%3A%2F%2Feggyolk.chaldal.com%2Fapi%2FPicture%2FRaw%3FpictureId%3D40628&q=low&v=1"
        ],
        "price": 250.0,
        "corpPrice": 250.0,
        "objectID": 6996
    },
    {
        "category": {
            "name": "Men's Facewash",
            "id": "1498",
            "slug": "mens-facewash"
        },
        "bengaliName": "\u09ae\u09cd\u09af\u09be\u09a8\u09b8 \u0997\u09cd\u09b2\u09cb \u0985\u09cd\u09af\u09be\u09a8\u09cd\u09a1 \u09b9\u09cd\u09af\u09be\u09a8\u09cd\u09a1\u09b8\u09be\u09ae \u09ab\u09c7\u09b8 \u0993\u09df\u09be\u09b6 \u09b0\u200d\u09cd\u09af\u09be\u09aa\u09bf\u09a1 \u098f\u0995\u09b6\u09a8 \u09eb\u09e6 \u0997\u09cd\u09b0\u09be\u09ae",
        "longDesc": null,
        "name": "Mens Glow And Handsome Face Wash Rapid Action 50 gm",
        "nameWithoutSubText": "Mens Glow And Handsome Face Wash Rapid Action",
        "picturesUrls": [
            "https://chaldn.com/_mpimage/mens-glow-and-handsome-face-wash-rapid-action-50-gm?src=https%3A%2F%2Feggyolk.chaldal.com%2Fapi%2FPicture%2FRaw%3FpictureId%3D76189&q=low&v=1"
        ],
        "price": 90.0,
        "corpPrice": 90.0,
        "objectID": 6051
    }
]