[
    {
        "category": {
            "name": "Tissue & Wipes",
            "id": "41",
            "slug": "tissue-wipes"
        },
        "bengaliName": "\u09ac\u09b8\u09c1\u09a8\u09cd\u09a7\u09b0\u09be \u099f\u09df\u09b2\u09c7\u099f \u099f\u09bf\u09b8\u09cd\u09af\u09c1 \u09ea \u099f\u09bf",
        "longDesc": "Bashundhara Toilet Tissue is a product of Bashundhara Group. Bashundhara Toilet Tissue is so soft and easy to use. It has nice absorbing power and long lasting.",
        "name": "Bashundhara Toilet Tissue 4 pcs",
        "nameWithoutSubText": "Bashundhara Toilet Tissue",
        "picturesUrls": [
            "https://chaldn.com/_mpimage/bashundhara-toilet-tissue-4-pcs?src=https%3A%2F%2Feggyolk.chaldal.com%2Fapi%2FPicture%2FRaw%3FpictureId%3D49741&q=low&v=1"
        ],
        "price": 80.0,
        "corpPrice": 80.0,
        "objectID": 2145
    },
    {
        "category": {
            "name": "Tissue & Wipes",
            "id": "41",
            "slug": "tissue-wipes"
        },
        "bengaliName": "\u09ac\u09b8\u09c1\u09c1\u09a8\u09cd\u09a7\u09b0\u09be \u09aa\u09c7\u09aa\u09be\u09b0 \u09a8\u09cd\u09af\u09be\u09aa\u0995\u09bf\u09a8 \u09e7\u09e9\" \u0997\u09a8\u09cd\u09a7\u09ae\u09c1\u0995\u09cd\u09a4 (\u09e7\u09e6\u09e6 \u099f\u09bf)",
        "longDesc": "Bashundhara paper napkin  is a product of Bashundhara Group. Its too soft and easy to use. Bashundhara paper napkin has good absorption ability. 1 Packet Bashundhara paper napkin contain 13\"X 1 PLY Pcs.",
        "name": "Bashundhara Paper Napkins 13\" Unscented 100 pcs",
        "nameWithoutSubText": "Bashundhara Paper Napkins 13\" Unscented",
        "picturesUrls": [
            "https://chaldn.com/_mpimage/bashundhara-paper-napkins-13-unscented-100-pcs?src=https%3A%2F%2Feggyolk.chaldal.com%2Fapi%2FPicture%2FRaw%3FpictureId%3D80780&q=low&v=1"
        ],
        "price": 70.0,
        "corpPrice": 70.0,
        "objectID": 4373
    },
    {
        "category": {
            "name": "Tissue & Wipes",
            "id": "41",
            "slug": "tissue-wipes"
        },
        "bengaliName": "\u09ac\u09b8\u09c1\u09a8\u09cd\u09a7\u09b0\u09be \u09ab\u09c7\u09b8\u09bf\u09df\u09be\u09b2 \u099f\u09bf\u09b8\u09cd\u09af\u09c1 (\u099a\u09be\u09b2\u09a1\u09be\u09b2 \u09b2\u09cb\u0997\u09cb) \u09e7\u09e8\u09e6x\u09e8 \u09aa\u09cd\u09b2\u09be\u0987",
        "longDesc": "Brand: Bashundhara.\r\nProduct Type: Facial Tissue.\r\n120 x 2 Ply.\r\nBasic Raw Material: 100% Virgin pulp.",
        "name": "Bashundhara Facial Tissue (Chaldal Logo) 120X2 ply",
        "nameWithoutSubText": "Bashundhara Facial Tissue (Chaldal Logo) 120X2 ply",
        "picturesUrls": [
            "https://chaldn.com/_mpimage/bashundhara-facial-tissue-chaldal-logo-120x2-ply?src=https%3A%2F%2Feggyolk.chaldal.com%2Fapi%2FPicture%2FRaw%3FpictureId%3D49736&q=low&v=1"
        ],
        "price": 72.0,
        "corpPrice": 72.0,
        "objectID": 2144
    },
    {
        "category": {
            "name": "Tissue & Wipes",
            "id": "41",
            "slug": "tissue-wipes"
        },
        "bengaliName": "\u09ab\u09cd\u09b0\u09c7\u09b6 \u099f\u09df\u09b2\u09c7\u099f \u099f\u09bf\u09b8\u09cd\u09af\u09c1 (\u09ab\u09cd\u09af\u09be\u09ae\u09bf\u09b2\u09bf \u09ad\u09cd\u09af\u09be\u09b2\u09c1 \u09aa\u09cd\u09af\u09be\u0995) \u09ea \u099f\u09bf",
        "longDesc": null,
        "name": "Fresh Toilet Tissue (Family Value Pack) 4 pcs",
        "nameWithoutSubText": "Fresh Toilet Tissue (Family Value Pack)",
        "picturesUrls": [
            "https://chaldn.com/_mpimage/fresh-toilet-tissue-family-value-pack-4-pcs?src=https%3A%2F%2Feggyolk.chaldal.com%2Fapi%2FPicture%2FRaw%3FpictureId%3D70461&q=low&v=1"
        ],
        "price": 59.0,
        "corpPrice": 59.0,
        "objectID": 15577
    },
    {
        "category": {
            "name": "Tissue & Wipes",
            "id": "41",
            "slug": "tissue-wipes"
        },
        "bengaliName": "\u09ac\u09b8\u09c1\u09a8\u09cd\u09a7\u09b0\u09be \u0997\u09cb\u09b2\u09cd\u09a1 \u099f\u09df\u09b2\u09c7\u099f \u099f\u09bf\u09b8\u09cd\u09af\u09c1 \u09e7 \u099f\u09bf",
        "longDesc": "Bashundhara Gold Toilet Tissue is so soft and easy to use. Can be used for variety of needs. You can use them for cleaning, wiping, polishing,  and absorbing. Bashundhara Gold Toilet Tissue  are more absorbent than ordinary tissue.",
        "name": "Bashundhara Gold Toilet Tissue 1 pcs",
        "nameWithoutSubText": "Bashundhara Gold Toilet Tissue",
        "picturesUrls": [
            "https://chaldn.com/_mpimage/bashundhara-gold-toilet-tissue-1-pcs?src=https%3A%2F%2Feggyolk.chaldal.com%2Fapi%2FPicture%2FRaw%3FpictureId%3D64375&q=low&v=1"
        ],
        "price": 30.0,
        "corpPrice": 30.0,
        "objectID": 9445
    },
    {
        "category": {
            "name": "Tissue & Wipes",
            "id": "41",
            "slug": "tissue-wipes"
        },
        "bengaliName": "\u09ab\u09c7 \u09ab\u09c7\u09b8\u09bf\u09df\u09be\u09b2 \u099f\u09bf\u09b8\u09cd\u09af\u09c1 \u09e7\u09eb\u09e6x\u09e8 \u09aa\u09cd\u09b2\u09be\u0987 \u09ac\u0995\u09cd\u09b8 \u09e7 \u099f\u09bf",
        "longDesc": null,
        "name": "Fay Facial Tissue (150 X 2) ply Box 1 pcs",
        "nameWithoutSubText": "Fay Facial Tissue (150 X 2) ply Box",
        "picturesUrls": [
            "https://chaldn.com/_mpimage/fay-facial-tissue-150-x-2-ply-box-1-pcs?src=https%3A%2F%2Feggyolk.chaldal.com%2Fapi%2FPicture%2FRaw%3FpictureId%3D65880&q=low&v=1"
        ],
        "price": 80.0,
        "corpPrice": 80.0,
        "objectID": 2223
    },
    {
        "category": {
            "name": "Tissue & Wipes",
            "id": "41",
            "slug": "tissue-wipes"
        },
        "bengaliName": "\u09ab\u09cd\u09b0\u09c7\u09b6 \u09b8\u09c1\u0997\u09a8\u09cd\u09a7\u09bf\u09af\u09c1\u0995\u09cd\u09a4 \u09ab\u09c7\u09b8\u09bf\u09df\u09be\u09b2 \u099f\u09bf\u09b8\u09cd\u09af\u09c1 (\u09e7\u09eb\u09e6x\u09e8) \u09aa\u09cd\u09b2\u09be\u0987 \u09ac\u0995\u09cd\u09b8 \u09e7 \u099f\u09bf",
        "longDesc": null,
        "name": "Fresh Perfumed Facial Tissue (150 X 2) ply Box 1 pcs",
        "nameWithoutSubText": "Fresh Perfumed Facial Tissue (150 X 2) ply Box",
        "picturesUrls": [
            "https://chaldn.com/_mpimage/fresh-perfumed-facial-tissue-150-x-2-ply-box-1-pcs?src=https%3A%2F%2Feggyolk.chaldal.com%2Fapi%2FPicture%2FRaw%3FpictureId%3D49747&q=low&v=1"
        ],
        "price": 72.0,
        "corpPrice": 72.0,
        "objectID": 15578
    },
    {
        "category": {
            "name": "Tissue & Wipes",
            "id": "41",
            "slug": "tissue-wipes"
        },
        "bengaliName": "\u09ab\u09c7 \u099f\u09df\u09b2\u09c7\u099f \u099f\u09bf\u09b8\u09cd\u09af\u09c1 \u09e7 \u09aa\u09cd\u09af\u09be\u0995\u09c7\u099f",
        "longDesc": null,
        "name": "Fay Toilet Tissue 1 packet",
        "nameWithoutSubText": "Fay Toilet Tissue",
        "picturesUrls": [
            "https://chaldn.com/_mpimage/fay-toilet-tissue-1-packet?src=https%3A%2F%2Feggyolk.chaldal.com%2Fapi%2FPicture%2FRaw%3FpictureId%3D74393&q=low&v=1"
        ],
        "price": 22.0,
        "corpPrice": 22.0,
        "objectID": 2225
    },
    {
        "category": {
            "name": "Tissue & Wipes",
            "id": "41",
            "slug": "tissue-wipes"
        },
        "bengaliName": "\u09ab\u09cd\u09b0\u09c7\u09b6 \u09aa\u09c7\u09aa\u09be\u09b0 \u09a8\u09cd\u09af\u09be\u09aa\u0995\u09bf\u09a8 \u09e7\u09e9\" \u09b8\u09c1\u0997\u09a8\u09cd\u09a7\u09ae\u09c1\u0995\u09cd\u09a4 \u09e7\u09e6\u09e6X \u09e7 \u09aa\u09cd\u09b2\u09be\u0987 \u09e7 \u099f\u09bf ",
        "longDesc": null,
        "name": "Fresh Paper Napkins 13\" Perfumed (100X1 Ply) 1 pcs  ",
        "nameWithoutSubText": "Fresh Paper Napkins 13\" Perfumed (100X1 Ply)",
        "picturesUrls": [
            "https://chaldn.com/_mpimage/fresh-paper-napkins-13-perfumed-100x1-ply-1-pcs?src=https%3A%2F%2Feggyolk.chaldal.com%2Fapi%2FPicture%2FRaw%3FpictureId%3D49746&q=low&v=1"
        ],
        "price": 49.0,
        "corpPrice": 49.0,
        "objectID": 15579
    },
    {
        "category": {
            "name": "Tissue & Wipes",
            "id": "41",
            "slug": "tissue-wipes"
        },
        "bengaliName": "\u09ab\u09c7 \u09aa\u09be\u09b0\u09ab\u09bf\u0989\u09ae \u09ab\u09c7\u09b8\u09bf\u09af\u09bc\u09be\u09b2 \u099f\u09bf\u09b8\u09cd\u09af\u09c1 (\u09e7\u09eb\u09e6 \u098f\u0995\u09cd\u09b8 \u09e8 \u09aa\u09cd\u09b2\u09be\u0987) \u09e7 \u09ac\u0995\u09cd\u09b8",
        "longDesc": null,
        "name": "Fay Perfume Facial Tissue (150 X 2ply) 1 Box",
        "nameWithoutSubText": "Fay Perfume Facial Tissue (150 X 2ply) 1 Box",
        "picturesUrls": [
            "https://chaldn.com/_mpimage/fay-perfume-facial-tissue-150-x-2ply-1-box?src=https%3A%2F%2Feggyolk.chaldal.com%2Fapi%2FPicture%2FRaw%3FpictureId%3D65881&q=low&v=1"
        ],
        "price": 80.0,
        "corpPrice": 80.0,
        "objectID": 20511
    },
    {
        "category": {
            "name": "Tissue & Wipes",
            "id": "41",
            "slug": "tissue-wipes"
        },
        "bengaliName": "\u09aa\u09cd\u09b2\u09be\u09a8\u09c7\u099f \u09aa\u09be\u09b0\u09ab\u09bf\u0989\u09ae\u09a1 \u09ab\u09c7\u09b8\u09bf\u09df\u09be\u09b2 \u099f\u09bf\u09b8\u09cd\u09af\u09c1 (\u09e7\u09e8\u09e6X\u09e8) \u09aa\u09cd\u09b2\u09be\u0987  \u09ac\u0995\u09cd\u09b8 \u09e7\u099f\u09bf",
        "longDesc": null,
        "name": "Planet Perfumed Facial Tissue (120X2 ) Ply Box 1 pcs",
        "nameWithoutSubText": "Planet Perfumed Facial Tissue (120X2 ) Ply Box",
        "picturesUrls": [
            "https://chaldn.com/_mpimage/planet-perfumed-facial-tissue-120x2-ply-box-1-pcs?src=https%3A%2F%2Feggyolk.chaldal.com%2Fapi%2FPicture%2FRaw%3FpictureId%3D62870&q=low&v=1"
        ],
        "price": 62.0,
        "corpPrice": 62.0,
        "objectID": 22041
    },
    {
        "category": {
            "name": "Tissue & Wipes",
            "id": "41",
            "slug": "tissue-wipes"
        },
        "bengaliName": "\u09aa\u09cd\u09b2\u09be\u09a8\u09c7\u099f \u09aa\u09be\u09b0\u09ab\u09bf\u0989\u09ae\u09a1 \u09aa\u09cd\u09b0\u09bf\u09ae\u09bf\u09df\u09be\u09ae \u09a8\u09cd\u09af\u09be\u09aa\u0995\u09bf\u09a8 \u099f\u09bf\u09b8\u09cd\u09af\u09c1 \u09e7 \u09aa\u09bf\u09b8",
        "longDesc": null,
        "name": "Planet Perfumed Premium Napkin Tissue 1 pc",
        "nameWithoutSubText": "Planet Perfumed Premium Napkin Tissue",
        "picturesUrls": [
            "https://chaldn.com/_mpimage/planet-perfumed-premium-napkin-tissue-1-pc?src=https%3A%2F%2Feggyolk.chaldal.com%2Fapi%2FPicture%2FRaw%3FpictureId%3D66065&q=best&v=1"
        ],
        "price": 62.0,
        "corpPrice": 62.0,
        "objectID": 22356
    },
    {
        "category": {
            "name": "Tissue & Wipes",
            "id": "41",
            "slug": "tissue-wipes"
        },
        "bengaliName": "\u09a1\u09c7\u099f\u09b2 \u098f\u09a8\u09cd\u099f\u09bf \u09ac\u09cd\u09af\u09be\u0995\u09cd\u099f\u09c7\u09b0\u09bf\u09df\u09be\u09b2 \u09ad\u09c7\u099c\u09be \u099f\u09bf\u09b8\u09c1 \u09e7\u09e6 \u099f\u09bf",
        "longDesc": "Usage; Wiping your hands on-the-go, Before / after eating, For outdoor activities, Before / after using the toilet, At offices and schools, In the car of while travelling. Product Information: Dettol's trusted anti-bacterial ingredients kill 99.9% of harmful germs, Protects from a wide range of unseen germs, Soft, textured fabric gently cleanses your skin withut irritation, Pre-moisturised with purified water, Leaves your skin feeling fresh with a light fragrance after use, Alcohol free, optical brightener free, formaldehyde free. 10 wipes in the pack.\t\t\t\t\t\t\t\t\t\t\t\t\t\t\t\t\t\t\t\t\t\t\t\t\t\t\t\t\t\t\t\r\n ",
        "name": "Dettol Anti Bacterial Wet Wipes 10 pcs",
        "nameWithoutSubText": "Dettol Anti Bacterial Wet Wipes",
        "picturesUrls": [
            "https://chaldn.com/_mpimage/dettol-anti-bacterial-wet-wipes-10-pcs?src=https%3A%2F%2Feggyolk.chaldal.com%2Fapi%2FPicture%2FRaw%3FpictureId%3D69886&q=low&v=1",
            "https://chaldn.com/_mpimage/dettol-anti-bacterial-wet-wipes-10-pcs?src=https%3A%2F%2Feggyolk.chaldal.com%2Fapi%2FPicture%2FRaw%3FpictureId%3D34026&q=best&v=1",
            "https://chaldn.com/_mpimage/dettol-anti-bacterial-wet-wipes-10-pcs?src=https%3A%2F%2Feggyolk.chaldal.com%2Fapi%2FPicture%2FRaw%3FpictureId%3D34027&q=best&v=1",
            "https://chaldn.com/_mpimage/dettol-anti-bacterial-wet-wipes-10-pcs?src=https%3A%2F%2Feggyolk.chaldal.com%2Fapi%2FPicture%2FRaw%3FpictureId%3D34028&q=best&v=1",
            "https://chaldn.com/_mpimage/dettol-anti-bacterial-wet-wipes-10-pcs?src=https%3A%2F%2Feggyolk.chaldal.com%2Fapi%2FPicture%2FRaw%3FpictureId%3D34029&q=best&v=1",
            "https://chaldn.com/_mpimage/dettol-anti-bacterial-wet-wipes-10-pcs?src=https%3A%2F%2Feggyolk.chaldal.com%2Fapi%2FPicture%2FRaw%3FpictureId%3D34030&q=best&v=1",
            "https://chaldn.com/_mpimage/dettol-anti-bacterial-wet-wipes-10-pcs?src=https%3A%2F%2Feggyolk.chaldal.com%2Fapi%2FPicture%2FRaw%3FpictureId%3D34031&q=best&v=1"
        ],
        "price": 69.0,
        "corpPrice": 69.0,
        "objectID": 12915
    },
    {
        "category": {
            "name": "Tissue & Wipes",
            "id": "41",
            "slug": "tissue-wipes"
        },
        "bengaliName": "\u09aa\u09cd\u09b2\u09be\u09a8\u09c7\u099f \u0997\u09cb\u09b2\u09cd\u09a1 \u099f\u09df\u09b2\u09c7\u099f \u099f\u09bf\u09b8\u09cd\u09af\u09c1 \u09e7 \u09aa\u09bf\u09b8",
        "longDesc": null,
        "name": "Planet Gold Toilet Tissue 1 pc",
        "nameWithoutSubText": "Planet Gold Toilet Tissue",
        "picturesUrls": [
            "https://chaldn.com/_mpimage/planet-gold-toilet-tissue-1-pc?src=https%3A%2F%2Feggyolk.chaldal.com%2Fapi%2FPicture%2FRaw%3FpictureId%3D66043&q=best&v=1"
        ],
        "price": 26.0,
        "corpPrice": 26.0,
        "objectID": 22339
    },
    {
        "category": {
            "name": "Tissue & Wipes",
            "id": "41",
            "slug": "tissue-wipes"
        },
        "bengaliName": "\u09b2\u09be\u0987\u09ab\u09ac\u09df \u098f\u09a8\u09cd\u099f\u09bf\u09ac\u09cd\u09af\u09be\u0995\u09cd\u099f\u09c7\u09b0\u09bf\u09df\u09be\u09b2 \u0993\u09df\u09c7\u099f \u0989\u0987\u09aa\u09b8 (\u09ad\u09c7\u099c\u09be \u099f\u09bf\u09b8\u09cd\u09af\u09c1) \u09e7\u09e6 \u099f\u09bf",
        "longDesc": "Origin: India\r\nWhether you are out for a meal with friends, playing with your kids at the park or out travelling the world, Lifebuoy Antibacterial Wet Wipes is your trusted on-the-go hygiene buddy to wipe away germs, while refreshing your skin. So go ahead, get messy! \r\n\u2022\tFor gentle germ protection on-the-go\r\n\u2022\tWith vitamin E\r\n\u2022\tSkin pH Balanced\r\n\u2022\tSuitable for travel, meals, sports, and outdoor.\r\n\u2022\tGently cleanses hand, body, and face.\r\n\u2022\tMade from biodegradable fiber",
        "name": "Lifebuoy Antibacterial Wet Wipes 10 pcs",
        "nameWithoutSubText": "Lifebuoy Antibacterial Wet Wipes",
        "picturesUrls": [
            "https://chaldn.com/_mpimage/lifebuoy-antibacterial-wet-wipes-10-pcs?src=https%3A%2F%2Feggyolk.chaldal.com%2Fapi%2FPicture%2FRaw%3FpictureId%3D73702&q=low&v=1",
            "https://chaldn.com/_mpimage/lifebuoy-antibacterial-wet-wipes-10-pcs?src=https%3A%2F%2Feggyolk.chaldal.com%2Fapi%2FPicture%2FRaw%3FpictureId%3D73703&q=low&v=1",
            "https://chaldn.com/_mpimage/lifebuoy-antibacterial-wet-wipes-10-pcs?src=https%3A%2F%2Feggyolk.chaldal.com%2Fapi%2FPicture%2FRaw%3FpictureId%3D73704&q=low&v=1",
            "https://chaldn.com/_mpimage/lifebuoy-antibacterial-wet-wipes-10-pcs?src=https%3A%2F%2Feggyolk.chaldal.com%2Fapi%2FPicture%2FRaw%3FpictureId%3D73705&q=low&v=1"
        ],
        "price": 70.0,
        "corpPrice": 70.0,
        "objectID": 23597
    },
    {
        "category": {
            "name": "Tissue & Wipes",
            "id": "41",
            "slug": "tissue-wipes"
        },
        "bengaliName": "\u09a8\u09bf\u0993\u0995\u09c7\u09df\u09be\u09b0 \u09a1\u09bf\u09b8\u0987\u09a8\u09ab\u09c7\u0995\u099f\u09be\u09a8\u09cd\u099f \u0993\u09df\u09be\u099f \u0993\u09df\u09be\u0987\u09aa\u09cd\u09b8 \u09e8\u09eb \u099f\u09bf",
        "longDesc": "Origin: Bangladesh\r\nPH balanced, microbiologically tested disinfecting wipes. Capable of killing harmful virus and bacteria. Can be used as an alternative of hand sanitizer. Free from paraben, silicone and alcohol.\r\n\r\nQuantity: 25 Pcs",
        "name": "Neocare Disinfectant Wipes 25 pcs ",
        "nameWithoutSubText": "Neocare Disinfectant Wipes",
        "picturesUrls": [
            "https://chaldn.com/_mpimage/neocare-disinfectant-wipes-25-pcs?src=https%3A%2F%2Feggyolk.chaldal.com%2Fapi%2FPicture%2FRaw%3FpictureId%3D64655&q=low&v=1"
        ],
        "price": 125.0,
        "corpPrice": 125.0,
        "objectID": 22097
    },
    {
        "category": {
            "name": "Tissue & Wipes",
            "id": "41",
            "slug": "tissue-wipes"
        },
        "bengaliName": "\u09a1\u09c7\u099f\u09b2 \u0985\u09cd\u09af\u09be\u09a8\u09cd\u099f\u09bf-\u09ac\u09cd\u09af\u09be\u0995\u099f\u09c7\u09b0\u09bf\u09af\u09bc\u09be\u09b2 \u0993\u09af\u09bc\u09c7\u099f \u0989\u0987\u09aa\u09b8 \u09ab\u09cd\u09af\u09be\u09ae\u09bf\u09b2\u09bf \u09aa\u09cd\u09af\u09be\u0995 (\u09ec x\u09e7\u09e6) \u09ec\u09e6 \u099f\u09bf",
        "longDesc": "Dettol Anti-bacterial Wet Wipes Family Pack X 6 Pack\r\n\r\n\r\n\r\nDettol Wet Wipes are pre-moisturised with purified water. The soft, textured fabric gently cleanses your skin without irritation. Use anytime, anywhere: while in car, office, handbag, picnics, nappy change, travel, sports etc. Dettol is recommended by Doctors of Bangladesh Private Medical Practitioners Association (BPMPA). Dettol & Sword devices are registered trademark of Reckitt Benckiser Group PLC. Dettol is protecting health for over 80 years and is used 2 billion times each day in over 124 countries. Dettol Wipes in Bangladesh is manufactured in China and marketed by Reckitt Benckiser Bangladesh Limited.   ",
        "name": "Dettol Anti-bacterial Wet Wipes Family Pack (6 x10pcs) 60 pcs",
        "nameWithoutSubText": "Dettol Anti-bacterial Wet Wipes Family Pack (6 x10pcs)",
        "picturesUrls": [
            "https://chaldn.com/_mpimage/dettol-anti-bacterial-wet-wipes-family-pack-6-x10pcs-60-pcs?src=https%3A%2F%2Feggyolk.chaldal.com%2Fapi%2FPicture%2FRaw%3FpictureId%3D70399&q=low&v=1",
            "https://chaldn.com/_mpimage/dettol-anti-bacterial-wet-wipes-family-pack-combo?src=https%3A%2F%2Feggyolk.chaldal.com%2Fapi%2FPicture%2FRaw%3FpictureId%3D64272&q=low&v=1",
            "https://chaldn.com/_mpimage/dettol-anti-bacterial-wet-wipes-family-pack-combo?src=https%3A%2F%2Feggyolk.chaldal.com%2Fapi%2FPicture%2FRaw%3FpictureId%3D64273&q=low&v=1",
            "https://chaldn.com/_mpimage/dettol-anti-bacterial-wet-wipes-family-pack-combo?src=https%3A%2F%2Feggyolk.chaldal.com%2Fapi%2FPicture%2FRaw%3FpictureId%3D64274&q=low&v=1",
            "https://chaldn.com/_mpimage/dettol-anti-bacterial-wet-wipes-family-pack-combo?src=https%3A%2F%2Feggyolk.chaldal.com%2Fapi%2FPicture%2FRaw%3FpictureId%3D64275&q=low&v=1",
            "https://chaldn.com/_mpimage/dettol-anti-bacterial-wet-wipes-family-pack-combo?src=https%3A%2F%2Feggyolk.chaldal.com%2Fapi%2FPicture%2FRaw%3FpictureId%3D64276&q=low&v=1",
            "https://chaldn.com/_mpimage/dettol-anti-bacterial-wet-wipes-family-pack-combo?src=https%3A%2F%2Feggyolk.chaldal.com%2Fapi%2FPicture%2FRaw%3FpictureId%3D64277&q=low&v=1"
        ],
        "price": 389.0,
        "corpPrice": 389.0,
        "objectID": 22112
    },
    {
        "category": {
            "name": "Tissue & Wipes",
            "id": "41",
            "slug": "tissue-wipes"
        },
        "bengaliName": "\u09ab\u09c7 \u09aa\u09c7\u09aa\u09be\u09b0 \u09a8\u09cd\u09af\u09be\u09aa\u0995\u09bf\u09a8 \u09e7\u09e9\"(\u09ee\u09e6 X \u09e7\u09aa\u09cd\u09b2\u09be\u0987) \u09e7 \u09aa\u09bf\u09b8",
        "longDesc": null,
        "name": "Fay Paper Napkin 13'' (80 X 1ply) 1 pcs",
        "nameWithoutSubText": "Fay Paper Napkin 13'' (80 X 1ply)",
        "picturesUrls": [
            "https://chaldn.com/_mpimage/fay-paper-napkin-13-80-x-1ply-1-pcs?src=https%3A%2F%2Feggyolk.chaldal.com%2Fapi%2FPicture%2FRaw%3FpictureId%3D61520&q=low&v=1"
        ],
        "price": 60.0,
        "corpPrice": 60.0,
        "objectID": 20510
    },
    {
        "category": {
            "name": "Tissue & Wipes",
            "id": "41",
            "slug": "tissue-wipes"
        },
        "bengaliName": "\u09aa\u09cd\u09b2\u09be\u09a8\u09c7\u099f \u0993\u09df\u09c7\u09a1\u09bf\u0982 \u09b8\u09cd\u09aa\u09c7\u09b6\u09be\u09b2 \u09ab\u09c7\u09b8\u09bf\u09df\u09be\u09b2 \u099f\u09bf\u09b8\u09cd\u09af\u09c1 \u09e7 \u09aa\u09bf\u09b8",
        "longDesc": null,
        "name": "Planet Wedding Special Facial Tissue 1 Pcs",
        "nameWithoutSubText": "Planet Wedding Special Facial Tissue",
        "picturesUrls": [
            "https://chaldn.com/_mpimage/planet-wedding-special-facial-tissue-1-pcs?src=https%3A%2F%2Feggyolk.chaldal.com%2Fapi%2FPicture%2FRaw%3FpictureId%3D68289&q=best&v=1"
        ],
        "price": 45.0,
        "corpPrice": 45.0,
        "objectID": 22341
    },
    {
        "category": {
            "name": "Tissue & Wipes",
            "id": "41",
            "slug": "tissue-wipes"
        },
        "bengaliName": "\u0995\u09cd\u09b0\u09bf\u09ae \u09e8\u09e7 \u09b8\u09cd\u09af\u09be\u09a8\u09bf\u099f\u09be\u0987\u099c\u09be\u09b0 \u0989\u0987\u09aa\u09b8 \u09e7\u09e6 \u099f\u09bf",
        "longDesc": null,
        "name": "Creme 21 Sanitizer Wipes 10 pcs ",
        "nameWithoutSubText": "Creme 21 Sanitizer Wipes",
        "picturesUrls": [
            "https://chaldn.com/_mpimage/creme-21-sanitizer-wipes-10-pcs?src=https%3A%2F%2Feggyolk.chaldal.com%2Fapi%2FPicture%2FRaw%3FpictureId%3D73782&q=low&v=1"
        ],
        "price": 125.0,
        "corpPrice": 125.0,
        "objectID": 23631
    },
    {
        "category": {
            "name": "Tissue & Wipes",
            "id": "41",
            "slug": "tissue-wipes"
        },
        "bengaliName": "\u0997\u09cb\u09a1\u09b0\u09c7\u099c \u09aa\u09cd\u09b0\u09cb\u099f\u09c7\u0995\u09cd\u099f \u09b8\u09cd\u0995\u09bf\u09a8 \u0989\u0987\u09aa\u09b8 \u09e9\u09e6 \u099f\u09bf",
        "longDesc": null,
        "name": "Godrej Protect Skin Wipes 30 pcs",
        "nameWithoutSubText": "Godrej Protect Skin Wipes",
        "picturesUrls": [
            "https://chaldn.com/_mpimage/godrej-protect-skin-wipes-30-pcs?src=https%3A%2F%2Feggyolk.chaldal.com%2Fapi%2FPicture%2FRaw%3FpictureId%3D71833&q=low&v=1"
        ],
        "price": 160.0,
        "corpPrice": 160.0,
        "objectID": 23338
    },
    {
        "category": {
            "name": "Tissue & Wipes",
            "id": "41",
            "slug": "tissue-wipes"
        },
        "bengaliName": "\u0986\u09b2\u09cd\u099f\u09cd\u09b0\u09be \u0995\u09ae\u09cd\u09aa\u09cd\u09af\u09be\u0995\u09cd\u099f \u0993\u09df\u09c7\u099f \u0993\u09df\u09be\u0987\u09aa\u09cd\u09b8 \u09e7\u09e8\u09e6 \u09aa\u09bf\u09b8\u09c7\u09b8",
        "longDesc": "Origin -- Turkey",
        "name": "Ultra Compact Wet Wipes 120 pcs",
        "nameWithoutSubText": "Ultra Compact Wet Wipes",
        "picturesUrls": [
            "https://chaldn.com/_mpimage/ultra-compact-wet-wipes-120-pcs?src=https%3A%2F%2Feggyolk.chaldal.com%2Fapi%2FPicture%2FRaw%3FpictureId%3D67655&q=best&v=1"
        ],
        "price": 240.0,
        "corpPrice": 240.0,
        "objectID": 22496
    },
    {
        "category": {
            "name": "Tissue & Wipes",
            "id": "41",
            "slug": "tissue-wipes"
        },
        "bengaliName": "\u09aa\u09cd\u09b2\u09be\u09a8\u09c7\u099f \u09aa\u09be\u09b0\u09ab\u09bf\u0989\u09ae\u09a1 \u09aa\u0995\u09c7\u099f \u099f\u09bf\u09b8\u09cd\u09af\u09c1 \u09ee \u09aa\u09bf\u09b8\u09c7\u09b8",
        "longDesc": null,
        "name": "Planet Perfumed Pocket Tissue 8 pcs",
        "nameWithoutSubText": "Planet Perfumed Pocket Tissue",
        "picturesUrls": [
            "https://chaldn.com/_mpimage/planet-perfumed-pocket-tissue-8-pcs?src=https%3A%2F%2Feggyolk.chaldal.com%2Fapi%2FPicture%2FRaw%3FpictureId%3D66073&q=best&v=1"
        ],
        "price": 96.0,
        "corpPrice": 96.0,
        "objectID": 22357
    },
    {
        "category": {
            "name": "Tissue & Wipes",
            "id": "41",
            "slug": "tissue-wipes"
        },
        "bengaliName": "\u09aa\u09cd\u09b2\u09cd\u09af\u09be\u09a8\u09c7\u099f \u09aa\u0995\u09c7\u099f \u099f\u09bf\u09b8\u09cd\u09af\u09c1 (\u09e7\u09e6X\u09e8 \u09aa\u09cd\u09b2\u09be\u0987) \u09ee \u09aa\u09bf\u09b8",
        "longDesc": null,
        "name": "Planet Pocket Tissue (10X2 Ply) 8 pcs",
        "nameWithoutSubText": "Planet Pocket Tissue (10X2 Ply)",
        "picturesUrls": [
            "https://chaldn.com/_mpimage/planet-pocket-tissue-10x2-ply-8-pcs?src=https%3A%2F%2Feggyolk.chaldal.com%2Fapi%2FPicture%2FRaw%3FpictureId%3D62948&q=low&v=1"
        ],
        "price": 96.0,
        "corpPrice": 96.0,
        "objectID": 22070
    },
    {
        "category": {
            "name": "Tissue & Wipes",
            "id": "41",
            "slug": "tissue-wipes"
        },
        "bengaliName": "\u09ab\u09c7 \u09ae\u09be\u09b2\u09cd\u099f\u09bf-\u09ab\u09cb\u09b2\u09cd\u09a1 \u09a4\u09cb\u09af\u09bc\u09be\u09b2\u09c7 \u09e7\u09eb\u09e6x\u09e7 \u09aa\u09cd\u09b2\u09be\u0987 \u09ac\u0995\u09cd\u09b8 \u09e7 \u099f\u09bf",
        "longDesc": null,
        "name": "Fay Multi-Fold Towel (150 X 1) Ply Box 1 pcs",
        "nameWithoutSubText": "Fay Multi-Fold Towel (150 X 1) Ply Box",
        "picturesUrls": [
            "https://chaldn.com/_mpimage/fay-multi-fold-towel-150-x-1-ply-box-1-pcs?src=https%3A%2F%2Feggyolk.chaldal.com%2Fapi%2FPicture%2FRaw%3FpictureId%3D53363&q=best&v=1"
        ],
        "price": 150.0,
        "corpPrice": 150.0,
        "objectID": 20380
    },
    {
        "category": {
            "name": "Tissue & Wipes",
            "id": "41",
            "slug": "tissue-wipes"
        },
        "bengaliName": " \u09ab\u09cd\u09b2\u09cb\u09ae\u09be\u09b0\u09be\u09b0 \u09ae\u09c7\u0995\u0986\u09aa \u09b0\u09bf\u09ae\u09c1\u09ad\u09be\u09b0 \u0993\u09af\u09bc\u09c7\u099f \u0993\u09af\u09bc\u09c7\u09aa\u09b8 \u09e8\u09e6 \u099f\u09bf",
        "longDesc": "Origin: Turkey\r\nClean Care Make-Up Wet Wipes allow you to easily remove your make-up without leaving an oily layer or any residues. Flormar make-up wipes leave your skin feeling moisturized and refreshed.\r\n\r\nQuantity: 20 pcs\r\n\r\n\"\u0989\u09ce\u09aa\u09be\u09a6\u09a8\u0995\u09be\u09b0\u09c0 \u09a6\u09c7\u09b6\u0983 \u09a4\u09c1\u09b0\u09b8\u09cd\u0995\r\n\u098f\u0987 \u09ae\u09c7\u0995\u0986\u09aa \u09b0\u09bf\u09ae\u09c1\u09ad\u09be\u09b0 \u0993\u09df\u09be\u0987\u09aa\u0997\u09c1\u09b2\u09cb \u09a6\u09bf\u09df\u09c7 \u0996\u09c1\u09ac \u09b8\u09b9\u099c\u09c7\u0987 \u09a8\u09bf\u0996\u09c1\u0981\u09a4\u09ad\u09be\u09ac\u09c7 \u09ae\u09c7\u0995\u0986\u09aa \u09a4\u09cb\u09b2\u09be \u09af\u09be\u09ac\u09c7\u0964 \u0995\u09cb\u09a8\u09cb \u09a4\u09c7\u09b2 \u09ac\u09be \u09ae\u09df\u09b2\u09be\u09b0 \u09b8\u09cd\u09a4\u09b0 \u09a4\u09cd\u09ac\u0995\u09c7 \u09b2\u09c7\u0997\u09c7 \u09a5\u09be\u0995\u09ac\u09c7 \u09a8\u09be\u0964 \u0986\u09aa\u09a8\u09be\u09b0 \u09a4\u09cd\u09ac\u0995\u0995\u09c7 \u09ae\u09df\u09c7\u09b6\u09cd\u099a\u09be\u09b0\u09be\u0987\u099c\u09be\u09b0\u09c7\u09b0 \u09aa\u09cd\u09b0\u09b2\u09c7\u09aa \u09a6\u09bf\u09df\u09c7 \u09b0\u09bf\u09ab\u09cd\u09b0\u09c7\u09b6 \u0995\u09b0\u09a4\u09c7 \u099a\u09be\u0987\u09b2\u09c7 \u09ac\u09cd\u09af\u09ac\u09b9\u09be\u09b0 \u0995\u09b0\u09c1\u09a8 \u09ab\u09cd\u09b2\u09cb\u09b0\u09ae\u09be\u09b0 \u09ae\u09c7\u0995\u0986\u09aa \u09b0\u09bf\u09ae\u09c1\u09ad\u09be\u09b0 \u0993\u09df\u09c7\u099f \u0993\u09df\u09be\u0987\u09aa\u09cd\u09b8  \u0964     \r\n\u09aa\u09b0\u09bf\u09ae\u09be\u09a3\u0983 \u09e8\u09e6 \u09aa\u09bf\u09b8\r\n\"",
        "name": "Flormar Makeup Remover Wet Wipes 20 pcs",
        "nameWithoutSubText": "Flormar Makeup Remover Wet Wipes",
        "picturesUrls": [
            "https://chaldn.com/_mpimage/flormar-makeup-remover-wet-wipes-20-pcs?src=https%3A%2F%2Feggyolk.chaldal.com%2Fapi%2FPicture%2FRaw%3FpictureId%3D50600&q=low&v=1"
        ],
        "price": 400.0,
        "corpPrice": 400.0,
        "objectID": 18719
    },
    {
        "category": {
            "name": "Tissue & Wipes",
            "id": "41",
            "slug": "tissue-wipes"
        },
        "bengaliName": "\u09ab\u09cd\u09b2\u09cb\u09b0\u09ae\u09be\u09b0 \u0995\u09cd\u09b2\u09bf\u09a8 \u0995\u09c7\u09af\u09bc\u09be\u09b0 \u09ae\u09c7\u0995\u0986\u09aa \u0993\u09af\u09bc\u09c7\u099f \u099f\u09bf\u09b8\u09cd\u09af\u09c1 \u09e8\u09e6 \u099f\u09bf",
        "longDesc": "Origin: Turkey\r\nThanks to Flormar Clean Care Wet Wipes, which helps you deeply cleanse the pores and allow them to breathe so they can remain healthy, you can easily remove face makeup with gentle touches. Clean Care Wet Wipes, which offer easy eye and face makeup removal, removes makeup entirely without leaving a layer of oil or residue on your face. You can easily use Clean Care Wet Wipes with moisturizing ingredients wherever you please and carry them around in your bag. \r\nQuantity: 20 pcs\r\n\r\n\r\n\"\u0989\u09ce\u09aa\u09be\u09a6\u09a8\u0995\u09be\u09b0\u09c0 \u09a6\u09c7\u09b6\u0983 \u09a4\u09c1\u09b0\u09b8\u09cd\u0995\r\n\u098f\u0987 \u09ae\u09c7\u0995\u0986\u09aa \u09b0\u09bf\u09ae\u09c1\u09ad\u09be\u09b0 \u0993\u09df\u09be\u0987\u09aa\u0997\u09c1\u09b2\u09cb \u09a6\u09bf\u09df\u09c7 \u0996\u09c1\u09ac \u09b8\u09b9\u099c\u09c7\u0987 \u09a8\u09bf\u0996\u09c1\u0981\u09a4\u09ad\u09be\u09ac\u09c7 \u09ae\u09c7\u0995\u0986\u09aa \u09a4\u09cb\u09b2\u09be \u09af\u09be\u09ac\u09c7\u0964 \u0995\u09cb\u09a8\u09cb \u09a4\u09c7\u09b2 \u09ac\u09be \u09ae\u09df\u09b2\u09be\u09b0 \u09b8\u09cd\u09a4\u09b0 \u09a4\u09cd\u09ac\u0995\u09c7 \u09b2\u09c7\u0997\u09c7 \u09a5\u09be\u0995\u09ac\u09c7 \u09a8\u09be\u0964 \u0986\u09aa\u09a8\u09be\u09b0 \u09a4\u09cd\u09ac\u0995\u0995\u09c7 \u09ae\u09df\u09c7\u09b6\u09cd\u099a\u09be\u09b0\u09be\u0987\u099c\u09be\u09b0\u09c7\u09b0 \u09aa\u09cd\u09b0\u09b2\u09c7\u09aa \u09a6\u09bf\u09df\u09c7 \u09b0\u09bf\u09ab\u09cd\u09b0\u09c7\u09b6 \u0995\u09b0\u09a4\u09c7 \u099a\u09be\u0987\u09b2\u09c7 \u09ac\u09cd\u09af\u09ac\u09b9\u09be\u09b0 \u0995\u09b0\u09c1\u09a8 \u09ab\u09cd\u09b2\u09cb\u09b0\u09ae\u09be\u09b0 \u09ae\u09c7\u0995\u0986\u09aa \u09b0\u09bf\u09ae\u09c1\u09ad\u09be\u09b0 \u0993\u09df\u09c7\u099f \u0993\u09df\u09be\u0987\u09aa\u09cd\u09b8  \u0964     \r\n\u09aa\u09b0\u09bf\u09ae\u09be\u09a3\u0983 \u09e8\u09e6 \u09aa\u09bf\u09b8\r\n\"",
        "name": "Flormar Clean Care Makeup Wet Wipes 20 pcs",
        "nameWithoutSubText": "Flormar Clean Care Makeup Wet Wipes",
        "picturesUrls": [
            "https://chaldn.com/_mpimage/flormar-clean-care-makeup-wet-wipes-20-pcs?src=https%3A%2F%2Feggyolk.chaldal.com%2Fapi%2FPicture%2FRaw%3FpictureId%3D50599&q=low&v=1"
        ],
        "price": 300.0,
        "corpPrice": 300.0,
        "objectID": 18718
    },
    {
        "category": {
            "name": "Tissue & Wipes",
            "id": "41",
            "slug": "tissue-wipes"
        },
        "bengaliName": "\u09ab\u09cd\u09b0\u09c7\u09b6 \u09b8\u09c1\u0997\u09a8\u09cd\u09a7\u09af\u09c1\u0995\u09cd\u09a4 \u0993\u09df\u09be\u09b2\u09c7\u099f \u099f\u09bf\u09b8\u09cd\u09af\u09c1 (\u09e7\u09e6X\u09e8 \u09aa\u09cd\u09b2\u09be\u0987) \u09e7 \u099f\u09bf ",
        "longDesc": null,
        "name": "Fresh Perfumed Wallet Tissue (10X2 Ply) 1 pcs",
        "nameWithoutSubText": "Fresh Perfumed Wallet Tissue (10X2 Ply)",
        "picturesUrls": [
            "https://chaldn.com/_mpimage/fresh-perfumed-wallet-tissue-10x2-ply-1-pcs?src=https%3A%2F%2Feggyolk.chaldal.com%2Fapi%2FPicture%2FRaw%3FpictureId%3D70462&q=low&v=1"
        ],
        "price": 9.0,
        "corpPrice": 9.0,
        "objectID": 15583
    }
]